{
  "dataset": "charades",
  "model_names": [
    "CPL_Fusion",
    "CPL_DMVS"
  ],
  "num_samples": 3158,
  "iou_thresholds": [
    0.3,
    0.5,
    0.7
  ],
  "dimension_results": {
    "query_length_bucket": {
      "dimension": "query_length_bucket",
      "num_slices": 3,
      "slices": {
        "long(11-15)": {
          "count": 1,
          "ratio": 0.00031665611146295124,
          "models": {
            "CPL_Fusion": {
              "R@1,IoU=0.3": 1.0,
              "R@1,IoU=0.5": 1.0,
              "R@1,IoU=0.7": 0.0,
              "mIoU": 0.538775005750797,
              "count": 1,
              "R@5,mIoU": 0.8421914437859077,
              "R@5,IoU=0.3": 1.0,
              "R@5,IoU=0.5": 1.0,
              "R@5,IoU=0.7": 1.0
            },
            "CPL_DMVS": {
              "R@1,IoU=0.3": 0.0,
              "R@1,IoU=0.5": 0.0,
              "R@1,IoU=0.7": 0.0,
              "mIoU": 0.17461499270367373,
              "count": 1,
              "R@5,mIoU": 0.47090760207207655,
              "R@5,IoU=0.3": 1.0,
              "R@5,IoU=0.5": 0.0,
              "R@5,IoU=0.7": 0.0
            }
          }
        },
        "medium(6-10)": {
          "count": 1914,
          "ratio": 0.6060797973400887,
          "models": {
            "CPL_Fusion": {
              "R@1,IoU=0.3": 0.46342737722048066,
              "R@1,IoU=0.5": 0.2800417972831766,
              "R@1,IoU=0.7": 0.0851619644723093,
              "mIoU": 0.2963840464966984,
              "count": 1914,
              "R@5,mIoU": 0.6614445770483227,
              "R@5,IoU=0.3": 0.9670846394984326,
              "R@5,IoU=0.5": 0.8249738766980146,
              "R@5,IoU=0.7": 0.45141065830721006
            },
            "CPL_DMVS": {
              "R@1,IoU=0.3": 0.3709508881922675,
              "R@1,IoU=0.5": 0.23981191222570533,
              "R@1,IoU=0.7": 0.09822361546499478,
              "mIoU": 0.24366778495362412,
              "count": 1914,
              "R@5,mIoU": 0.6107411058139567,
              "R@5,IoU=0.3": 0.9085684430512017,
              "R@5,IoU=0.5": 0.7366771159874608,
              "R@5,IoU=0.7": 0.40752351097178685
            }
          }
        },
        "short(<=5)": {
          "count": 1243,
          "ratio": 0.39360354654844837,
          "models": {
            "CPL_Fusion": {
              "R@1,IoU=0.3": 0.41995172968624295,
              "R@1,IoU=0.5": 0.2711182622687047,
              "R@1,IoU=0.7": 0.07240547063555913,
              "mIoU": 0.2697655178964138,
              "count": 1243,
              "R@5,mIoU": 0.6468407877547783,
              "R@5,IoU=0.3": 0.9589702333065165,
              "R@5,IoU=0.5": 0.8181818181818182,
              "R@5,IoU=0.7": 0.413515687851971
            },
            "CPL_DMVS": {
              "R@1,IoU=0.3": 0.38857602574416733,
              "R@1,IoU=0.5": 0.252614641995173,
              "R@1,IoU=0.7": 0.10378117457763475,
              "mIoU": 0.25629830214927224,
              "count": 1243,
              "R@5,mIoU": 0.6025065628659018,
              "R@5,IoU=0.3": 0.909895414320193,
              "R@5,IoU=0.5": 0.7176186645213194,
              "R@5,IoU=0.7": 0.3893805309734513
            }
          }
        }
      }
    },
    "action_complexity": {
      "dimension": "action_complexity",
      "num_slices": 4,
      "slices": {
        "dual_action": {
          "count": 517,
          "ratio": 0.16371120962634578,
          "models": {
            "CPL_Fusion": {
              "R@1,IoU=0.3": 0.47195357833655704,
              "R@1,IoU=0.5": 0.2978723404255319,
              "R@1,IoU=0.7": 0.07930367504835589,
              "mIoU": 0.3014886533267314,
              "count": 517,
              "R@5,mIoU": 0.6574883012599545,
              "R@5,IoU=0.3": 0.9671179883945842,
              "R@5,IoU=0.5": 0.8007736943907157,
              "R@5,IoU=0.7": 0.4274661508704062
            },
            "CPL_DMVS": {
              "R@1,IoU=0.3": 0.4119922630560928,
              "R@1,IoU=0.5": 0.2611218568665377,
              "R@1,IoU=0.7": 0.09864603481624758,
              "mIoU": 0.2600841590522907,
              "count": 517,
              "R@5,mIoU": 0.6135220522733786,
              "R@5,IoU=0.3": 0.9148936170212766,
              "R@5,IoU=0.5": 0.7292069632495164,
              "R@5,IoU=0.7": 0.41392649903288203
            }
          }
        },
        "multi_action(3+)": {
          "count": 26,
          "ratio": 0.008233058898036731,
          "models": {
            "CPL_Fusion": {
              "R@1,IoU=0.3": 0.5,
              "R@1,IoU=0.5": 0.34615384615384615,
              "R@1,IoU=0.7": 0.07692307692307693,
              "mIoU": 0.2915804686418643,
              "count": 26,
              "R@5,mIoU": 0.5872667119570469,
              "R@5,IoU=0.3": 0.8461538461538461,
              "R@5,IoU=0.5": 0.7692307692307693,
              "R@5,IoU=0.7": 0.2692307692307692
            },
            "CPL_DMVS": {
              "R@1,IoU=0.3": 0.5,
              "R@1,IoU=0.5": 0.38461538461538464,
              "R@1,IoU=0.7": 0.038461538461538464,
              "mIoU": 0.2908326419559173,
              "count": 26,
              "R@5,mIoU": 0.589880149685409,
              "R@5,IoU=0.3": 0.9230769230769231,
              "R@5,IoU=0.5": 0.6923076923076923,
              "R@5,IoU=0.7": 0.38461538461538464
            }
          }
        },
        "no_verb": {
          "count": 234,
          "ratio": 0.0740975300823306,
          "models": {
            "CPL_Fusion": {
              "R@1,IoU=0.3": 0.5256410256410257,
              "R@1,IoU=0.5": 0.32051282051282054,
              "R@1,IoU=0.7": 0.08974358974358974,
              "mIoU": 0.3299405472756184,
              "count": 234,
              "R@5,mIoU": 0.6946201860675987,
              "R@5,IoU=0.3": 0.9914529914529915,
              "R@5,IoU=0.5": 0.8846153846153846,
              "R@5,IoU=0.7": 0.5213675213675214
            },
            "CPL_DMVS": {
              "R@1,IoU=0.3": 0.3547008547008547,
              "R@1,IoU=0.5": 0.2606837606837607,
              "R@1,IoU=0.7": 0.1452991452991453,
              "mIoU": 0.26147407729272254,
              "count": 234,
              "R@5,mIoU": 0.6400270214955283,
              "R@5,IoU=0.3": 0.9316239316239316,
              "R@5,IoU=0.5": 0.7863247863247863,
              "R@5,IoU=0.7": 0.4658119658119658
            }
          }
        },
        "single_action": {
          "count": 2381,
          "ratio": 0.7539582013932868,
          "models": {
            "CPL_Fusion": {
              "R@1,IoU=0.3": 0.4325913481730365,
              "R@1,IoU=0.5": 0.26711465770684584,
              "R@1,IoU=0.7": 0.07937841243175137,
              "mIoU": 0.27823585246895033,
              "count": 2381,
              "R@5,mIoU": 0.6523052084382055,
              "R@5,IoU=0.3": 0.9617807643847123,
              "R@5,IoU=0.5": 0.8215035699286014,
              "R@5,IoU=0.7": 0.43217135657286854
            },
            "CPL_DMVS": {
              "R@1,IoU=0.3": 0.37127257454850904,
              "R@1,IoU=0.5": 0.2381352372952541,
              "R@1,IoU=0.7": 0.09701805963880722,
              "mIoU": 0.2444029617631669,
              "count": 2381,
              "R@5,mIoU": 0.6031293296199874,
              "R@5,IoU=0.3": 0.9055018899622007,
              "R@5,IoU=0.5": 0.7236455270894582,
              "R@5,IoU=0.7": 0.3910121797564049
            }
          }
        }
      }
    },
    "action_category": {
      "dimension": "action_category",
      "num_slices": 15,
      "slices": {
        "interaction": {
          "count": 945,
          "ratio": 0.2992400253324889,
          "models": {
            "CPL_Fusion": {
              "R@1,IoU=0.3": 0.4201058201058201,
              "R@1,IoU=0.5": 0.2560846560846561,
              "R@1,IoU=0.7": 0.0835978835978836,
              "mIoU": 0.2758647514159408,
              "count": 945,
              "R@5,mIoU": 0.6567037583966862,
              "R@5,IoU=0.3": 0.9788359788359788,
              "R@5,IoU=0.5": 0.8476190476190476,
              "R@5,IoU=0.7": 0.4201058201058201
            },
            "CPL_DMVS": {
              "R@1,IoU=0.3": 0.364021164021164,
              "R@1,IoU=0.5": 0.2275132275132275,
              "R@1,IoU=0.7": 0.06666666666666667,
              "mIoU": 0.2383735160053643,
              "count": 945,
              "R@5,mIoU": 0.6167826750256211,
              "R@5,IoU=0.3": 0.9386243386243386,
              "R@5,IoU=0.5": 0.764021164021164,
              "R@5,IoU=0.7": 0.364021164021164
            }
          }
        },
        "interaction,movement": {
          "count": 63,
          "ratio": 0.019949335022165927,
          "models": {
            "CPL_Fusion": {
              "R@1,IoU=0.3": 0.5238095238095238,
              "R@1,IoU=0.5": 0.38095238095238093,
              "R@1,IoU=0.7": 0.1111111111111111,
              "mIoU": 0.35049150373447824,
              "count": 63,
              "R@5,mIoU": 0.6941136015092518,
              "R@5,IoU=0.3": 0.9682539682539683,
              "R@5,IoU=0.5": 0.8412698412698413,
              "R@5,IoU=0.7": 0.5555555555555556
            },
            "CPL_DMVS": {
              "R@1,IoU=0.3": 0.47619047619047616,
              "R@1,IoU=0.5": 0.30158730158730157,
              "R@1,IoU=0.7": 0.14285714285714285,
              "mIoU": 0.3227672587186127,
              "count": 63,
              "R@5,mIoU": 0.6460991263788747,
              "R@5,IoU=0.3": 0.9365079365079365,
              "R@5,IoU=0.5": 0.7619047619047619,
              "R@5,IoU=0.7": 0.49206349206349204
            }
          }
        },
        "interaction,movement,perception": {
          "count": 1,
          "ratio": 0.00031665611146295124,
          "models": {
            "CPL_Fusion": {
              "R@1,IoU=0.3": 1.0,
              "R@1,IoU=0.5": 0.0,
              "R@1,IoU=0.7": 0.0,
              "mIoU": 0.37135887592878414,
              "count": 1,
              "R@5,mIoU": 0.37135887592878414,
              "R@5,IoU=0.3": 1.0,
              "R@5,IoU=0.5": 0.0,
              "R@5,IoU=0.7": 0.0
            },
            "CPL_DMVS": {
              "R@1,IoU=0.3": 0.0,
              "R@1,IoU=0.5": 0.0,
              "R@1,IoU=0.7": 0.0,
              "mIoU": 0.0,
              "count": 1,
              "R@5,mIoU": 0.3487726973522907,
              "R@5,IoU=0.3": 1.0,
              "R@5,IoU=0.5": 0.0,
              "R@5,IoU=0.7": 0.0
            }
          }
        },
        "interaction,movement,state_change": {
          "count": 1,
          "ratio": 0.00031665611146295124,
          "models": {
            "CPL_Fusion": {
              "R@1,IoU=0.3": 1.0,
              "R@1,IoU=0.5": 0.0,
              "R@1,IoU=0.7": 0.0,
              "mIoU": 0.3848334820224984,
              "count": 1,
              "R@5,mIoU": 0.855460724802152,
              "R@5,IoU=0.3": 1.0,
              "R@5,IoU=0.5": 1.0,
              "R@5,IoU=0.7": 1.0
            },
            "CPL_DMVS": {
              "R@1,IoU=0.3": 0.0,
              "R@1,IoU=0.5": 0.0,
              "R@1,IoU=0.7": 0.0,
              "mIoU": 0.0,
              "count": 1,
              "R@5,mIoU": 0.8498588233875662,
              "R@5,IoU=0.3": 1.0,
              "R@5,IoU=0.5": 1.0,
              "R@5,IoU=0.7": 1.0
            }
          }
        },
        "interaction,perception": {
          "count": 56,
          "ratio": 0.01773274224192527,
          "models": {
            "CPL_Fusion": {
              "R@1,IoU=0.3": 0.6071428571428571,
              "R@1,IoU=0.5": 0.375,
              "R@1,IoU=0.7": 0.21428571428571427,
              "mIoU": 0.38631977806677675,
              "count": 56,
              "R@5,mIoU": 0.697464038894708,
              "R@5,IoU=0.3": 0.9821428571428571,
              "R@5,IoU=0.5": 0.8928571428571429,
              "R@5,IoU=0.7": 0.5357142857142857
            },
            "CPL_DMVS": {
              "R@1,IoU=0.3": 0.4642857142857143,
              "R@1,IoU=0.5": 0.21428571428571427,
              "R@1,IoU=0.7": 0.08928571428571429,
              "mIoU": 0.27845559865430464,
              "count": 56,
              "R@5,mIoU": 0.6496288704339427,
              "R@5,IoU=0.3": 0.9821428571428571,
              "R@5,IoU=0.5": 0.7678571428571429,
              "R@5,IoU=0.7": 0.4642857142857143
            }
          }
        },
        "interaction,perception,state_change": {
          "count": 2,
          "ratio": 0.0006333122229259025,
          "models": {
            "CPL_Fusion": {
              "R@1,IoU=0.3": 1.0,
              "R@1,IoU=0.5": 1.0,
              "R@1,IoU=0.7": 0.0,
              "mIoU": 0.5489915508725691,
              "count": 2,
              "R@5,mIoU": 0.6171179003404955,
              "R@5,IoU=0.3": 1.0,
              "R@5,IoU=0.5": 1.0,
              "R@5,IoU=0.7": 0.0
            },
            "CPL_DMVS": {
              "R@1,IoU=0.3": 0.5,
              "R@1,IoU=0.5": 0.5,
              "R@1,IoU=0.7": 0.0,
              "mIoU": 0.3112968909609421,
              "count": 2,
              "R@5,mIoU": 0.8162712539859145,
              "R@5,IoU=0.3": 1.0,
              "R@5,IoU=0.5": 1.0,
              "R@5,IoU=0.7": 1.0
            }
          }
        },
        "interaction,state_change": {
          "count": 49,
          "ratio": 0.01551614946168461,
          "models": {
            "CPL_Fusion": {
              "R@1,IoU=0.3": 0.3673469387755102,
              "R@1,IoU=0.5": 0.1836734693877551,
              "R@1,IoU=0.7": 0.04081632653061224,
              "mIoU": 0.2351218235541681,
              "count": 49,
              "R@5,mIoU": 0.6417721532255576,
              "R@5,IoU=0.3": 0.9591836734693877,
              "R@5,IoU=0.5": 0.7959183673469388,
              "R@5,IoU=0.7": 0.3673469387755102
            },
            "CPL_DMVS": {
              "R@1,IoU=0.3": 0.4489795918367347,
              "R@1,IoU=0.5": 0.30612244897959184,
              "R@1,IoU=0.7": 0.08163265306122448,
              "mIoU": 0.28497478919131136,
              "count": 49,
              "R@5,mIoU": 0.5910611980928656,
              "R@5,IoU=0.3": 0.8775510204081632,
              "R@5,IoU=0.5": 0.6938775510204082,
              "R@5,IoU=0.7": 0.3469387755102041
            }
          }
        },
        "movement": {
          "count": 325,
          "ratio": 0.10291323622545916,
          "models": {
            "CPL_Fusion": {
              "R@1,IoU=0.3": 0.38769230769230767,
              "R@1,IoU=0.5": 0.24615384615384617,
              "R@1,IoU=0.7": 0.055384615384615386,
              "mIoU": 0.25347006743864686,
              "count": 325,
              "R@5,mIoU": 0.6243471305107618,
              "R@5,IoU=0.3": 0.916923076923077,
              "R@5,IoU=0.5": 0.76,
              "R@5,IoU=0.7": 0.4
            },
            "CPL_DMVS": {
              "R@1,IoU=0.3": 0.47384615384615386,
              "R@1,IoU=0.5": 0.38153846153846155,
              "R@1,IoU=0.7": 0.19692307692307692,
              "mIoU": 0.32817514100396633,
              "count": 325,
              "R@5,mIoU": 0.6282938269671815,
              "R@5,IoU=0.3": 0.9046153846153846,
              "R@5,IoU=0.5": 0.7630769230769231,
              "R@5,IoU=0.7": 0.48
            }
          }
        },
        "movement,perception": {
          "count": 76,
          "ratio": 0.024065864471184292,
          "models": {
            "CPL_Fusion": {
              "R@1,IoU=0.3": 0.6052631578947368,
              "R@1,IoU=0.5": 0.39473684210526316,
              "R@1,IoU=0.7": 0.11842105263157894,
              "mIoU": 0.3816880531771547,
              "count": 76,
              "R@5,mIoU": 0.6985885194372765,
              "R@5,IoU=0.3": 0.9868421052631579,
              "R@5,IoU=0.5": 0.8552631578947368,
              "R@5,IoU=0.7": 0.5263157894736842
            },
            "CPL_DMVS": {
              "R@1,IoU=0.3": 0.42105263157894735,
              "R@1,IoU=0.5": 0.3157894736842105,
              "R@1,IoU=0.7": 0.13157894736842105,
              "mIoU": 0.2713933120779582,
              "count": 76,
              "R@5,mIoU": 0.659202378077556,
              "R@5,IoU=0.3": 0.9210526315789473,
              "R@5,IoU=0.5": 0.7894736842105263,
              "R@5,IoU=0.7": 0.5789473684210527
            }
          }
        },
        "movement,perception,state_change": {
          "count": 2,
          "ratio": 0.0006333122229259025,
          "models": {
            "CPL_Fusion": {
              "R@1,IoU=0.3": 0.5,
              "R@1,IoU=0.5": 0.5,
              "R@1,IoU=0.7": 0.0,
              "mIoU": 0.3242198813525652,
              "count": 2,
              "R@5,mIoU": 0.7451207180554138,
              "R@5,IoU=0.3": 1.0,
              "R@5,IoU=0.5": 1.0,
              "R@5,IoU=0.7": 0.5
            },
            "CPL_DMVS": {
              "R@1,IoU=0.3": 0.5,
              "R@1,IoU=0.5": 0.0,
              "R@1,IoU=0.7": 0.0,
              "mIoU": 0.24112902993003515,
              "count": 2,
              "R@5,mIoU": 0.738793295775648,
              "R@5,IoU=0.3": 1.0,
              "R@5,IoU=0.5": 1.0,
              "R@5,IoU=0.7": 0.5
            }
          }
        },
        "movement,state_change": {
          "count": 33,
          "ratio": 0.01044965167827739,
          "models": {
            "CPL_Fusion": {
              "R@1,IoU=0.3": 0.3333333333333333,
              "R@1,IoU=0.5": 0.24242424242424243,
              "R@1,IoU=0.7": 0.06060606060606061,
              "mIoU": 0.19752477698539078,
              "count": 33,
              "R@5,mIoU": 0.6501626130345415,
              "R@5,IoU=0.3": 0.9090909090909091,
              "R@5,IoU=0.5": 0.8181818181818182,
              "R@5,IoU=0.7": 0.48484848484848486
            },
            "CPL_DMVS": {
              "R@1,IoU=0.3": 0.45454545454545453,
              "R@1,IoU=0.5": 0.21212121212121213,
              "R@1,IoU=0.7": 0.06060606060606061,
              "mIoU": 0.2534786026419712,
              "count": 33,
              "R@5,mIoU": 0.6429139154856901,
              "R@5,IoU=0.3": 0.9393939393939394,
              "R@5,IoU=0.5": 0.8181818181818182,
              "R@5,IoU=0.7": 0.5454545454545454
            }
          }
        },
        "perception": {
          "count": 496,
          "ratio": 0.1570614312856238,
          "models": {
            "CPL_Fusion": {
              "R@1,IoU=0.3": 0.5806451612903226,
              "R@1,IoU=0.5": 0.37701612903225806,
              "R@1,IoU=0.7": 0.10080645161290322,
              "mIoU": 0.35336009208067465,
              "count": 496,
              "R@5,mIoU": 0.6979371227360025,
              "R@5,IoU=0.3": 0.9899193548387096,
              "R@5,IoU=0.5": 0.8770161290322581,
              "R@5,IoU=0.7": 0.5383064516129032
            },
            "CPL_DMVS": {
              "R@1,IoU=0.3": 0.3790322580645161,
              "R@1,IoU=0.5": 0.2540322580645161,
              "R@1,IoU=0.7": 0.12298387096774194,
              "mIoU": 0.2560467702664851,
              "count": 496,
              "R@5,mIoU": 0.635616632840542,
              "R@5,IoU=0.3": 0.9395161290322581,
              "R@5,IoU=0.5": 0.7560483870967742,
              "R@5,IoU=0.7": 0.4576612903225806
            }
          }
        },
        "perception,state_change": {
          "count": 68,
          "ratio": 0.021532615579480684,
          "models": {
            "CPL_Fusion": {
              "R@1,IoU=0.3": 0.45588235294117646,
              "R@1,IoU=0.5": 0.22058823529411764,
              "R@1,IoU=0.7": 0.07352941176470588,
              "mIoU": 0.26274470841578235,
              "count": 68,
              "R@5,mIoU": 0.6871610146939124,
              "R@5,IoU=0.3": 0.9852941176470589,
              "R@5,IoU=0.5": 0.8970588235294118,
              "R@5,IoU=0.7": 0.47058823529411764
            },
            "CPL_DMVS": {
              "R@1,IoU=0.3": 0.35294117647058826,
              "R@1,IoU=0.5": 0.20588235294117646,
              "R@1,IoU=0.7": 0.058823529411764705,
              "mIoU": 0.21152228691307565,
              "count": 68,
              "R@5,mIoU": 0.6325964716538147,
              "R@5,IoU=0.3": 0.9558823529411765,
              "R@5,IoU=0.5": 0.7794117647058824,
              "R@5,IoU=0.7": 0.35294117647058826
            }
          }
        },
        "state_change": {
          "count": 807,
          "ratio": 0.25554148195060167,
          "models": {
            "CPL_Fusion": {
              "R@1,IoU=0.3": 0.36926889714993805,
              "R@1,IoU=0.5": 0.22304832713754646,
              "R@1,IoU=0.7": 0.05947955390334572,
              "mIoU": 0.2434473559699109,
              "count": 807,
              "R@5,mIoU": 0.6185800340153694,
              "R@5,IoU=0.3": 0.9380421313506815,
              "R@5,IoU=0.5": 0.7521685254027262,
              "R@5,IoU=0.7": 0.3593556381660471
            },
            "CPL_DMVS": {
              "R@1,IoU=0.3": 0.3382899628252788,
              "R@1,IoU=0.5": 0.19206939281288724,
              "R@1,IoU=0.7": 0.07558859975216853,
              "mIoU": 0.21147317338808522,
              "count": 807,
              "R@5,mIoU": 0.5471764884009019,
              "R@5,IoU=0.3": 0.838909541511772,
              "R@5,IoU=0.5": 0.6232961586121437,
              "R@5,IoU=0.7": 0.3271375464684015
            }
          }
        },
        "unknown": {
          "count": 234,
          "ratio": 0.0740975300823306,
          "models": {
            "CPL_Fusion": {
              "R@1,IoU=0.3": 0.5256410256410257,
              "R@1,IoU=0.5": 0.32051282051282054,
              "R@1,IoU=0.7": 0.08974358974358974,
              "mIoU": 0.3299405472756184,
              "count": 234,
              "R@5,mIoU": 0.6946201860675987,
              "R@5,IoU=0.3": 0.9914529914529915,
              "R@5,IoU=0.5": 0.8846153846153846,
              "R@5,IoU=0.7": 0.5213675213675214
            },
            "CPL_DMVS": {
              "R@1,IoU=0.3": 0.3547008547008547,
              "R@1,IoU=0.5": 0.2606837606837607,
              "R@1,IoU=0.7": 0.1452991452991453,
              "mIoU": 0.26147407729272254,
              "count": 234,
              "R@5,mIoU": 0.6400270214955283,
              "R@5,IoU=0.3": 0.9316239316239316,
              "R@5,IoU=0.5": 0.7863247863247863,
              "R@5,IoU=0.7": 0.4658119658119658
            }
          }
        }
      }
    },
    "has_person_subject": {
      "dimension": "has_person_subject",
      "num_slices": 2,
      "slices": {
        "False": {
          "count": 3,
          "ratio": 0.0009499683343888537,
          "models": {
            "CPL_Fusion": {
              "R@1,IoU=0.3": 0.0,
              "R@1,IoU=0.5": 0.0,
              "R@1,IoU=0.7": 0.0,
              "mIoU": 0.057004781174471386,
              "count": 3,
              "R@5,mIoU": 0.5489792551748104,
              "R@5,IoU=0.3": 1.0,
              "R@5,IoU=0.5": 0.6666666666666666,
              "R@5,IoU=0.7": 0.0
            },
            "CPL_DMVS": {
              "R@1,IoU=0.3": 0.3333333333333333,
              "R@1,IoU=0.5": 0.0,
              "R@1,IoU=0.7": 0.0,
              "mIoU": 0.256999329875591,
              "count": 3,
              "R@5,mIoU": 0.6265552272492197,
              "R@5,IoU=0.3": 1.0,
              "R@5,IoU=0.5": 1.0,
              "R@5,IoU=0.7": 0.3333333333333333
            }
          }
        },
        "True": {
          "count": 3155,
          "ratio": 0.9990500316656111,
          "models": {
            "CPL_Fusion": {
              "R@1,IoU=0.3": 0.4469096671949287,
              "R@1,IoU=0.5": 0.27702060221870045,
              "R@1,IoU=0.7": 0.08019017432646593,
              "mIoU": 0.28620138332873235,
              "count": 3155,
              "R@5,mIoU": 0.6558552371879368,
              "R@5,IoU=0.3": 0.9638668779714739,
              "R@5,IoU=0.5": 0.8225039619651348,
              "R@5,IoU=0.7": 0.43708399366085576
            },
            "CPL_DMVS": {
              "R@1,IoU=0.3": 0.3778129952456418,
              "R@1,IoU=0.5": 0.2450079239302694,
              "R@1,IoU=0.7": 0.10047543581616482,
              "mIoU": 0.2486093651270551,
              "count": 3155,
              "R@5,mIoU": 0.6074375201554844,
              "R@5,IoU=0.3": 0.9090332805071315,
              "R@5,IoU=0.5": 0.7286846275752773,
              "R@5,IoU=0.7": 0.40031695721077654
            }
          }
        }
      }
    },
    "has_temporal_cue": {
      "dimension": "has_temporal_cue",
      "num_slices": 2,
      "slices": {
        "False": {
          "count": 3051,
          "ratio": 0.9661177960734643,
          "models": {
            "CPL_Fusion": {
              "R@1,IoU=0.3": 0.44837758112094395,
              "R@1,IoU=0.5": 0.27663061291379876,
              "R@1,IoU=0.7": 0.0776794493608653,
              "mIoU": 0.2863599876049548,
              "count": 3051,
              "R@5,mIoU": 0.6553900925942527,
              "R@5,IoU=0.3": 0.9639462471320879,
              "R@5,IoU=0.5": 0.8233366109472304,
              "R@5,IoU=0.7": 0.4336283185840708
            },
            "CPL_DMVS": {
              "R@1,IoU=0.3": 0.3743035070468699,
              "R@1,IoU=0.5": 0.24090462143559488,
              "R@1,IoU=0.7": 0.09832841691248771,
              "mIoU": 0.24594473802688335,
              "count": 3051,
              "R@5,mIoU": 0.6061209311383957,
              "R@5,IoU=0.3": 0.9088823336610947,
              "R@5,IoU=0.5": 0.7273025237627008,
              "R@5,IoU=0.7": 0.39593575876761716
            }
          }
        },
        "True": {
          "count": 107,
          "ratio": 0.033882203926535785,
          "models": {
            "CPL_Fusion": {
              "R@1,IoU=0.3": 0.3925233644859813,
              "R@1,IoU=0.5": 0.2803738317757009,
              "R@1,IoU=0.7": 0.14953271028037382,
              "mIoU": 0.2752528650743646,
              "count": 107,
              "R@5,mIoU": 0.666121855966354,
              "R@5,IoU=0.3": 0.9626168224299065,
              "R@5,IoU=0.5": 0.794392523364486,
              "R@5,IoU=0.7": 0.5233644859813084
            },
            "CPL_DMVS": {
              "R@1,IoU=0.3": 0.4766355140186916,
              "R@1,IoU=0.5": 0.35514018691588783,
              "R@1,IoU=0.7": 0.1588785046728972,
              "mIoU": 0.3248238247239675,
              "count": 107,
              "R@5,mIoU": 0.6455147744771575,
              "R@5,IoU=0.3": 0.9158878504672897,
              "R@5,IoU=0.5": 0.7757009345794392,
              "R@5,IoU=0.7": 0.5233644859813084
            }
          }
        }
      }
    },
    "gt_coverage_bucket": {
      "dimension": "gt_coverage_bucket",
      "num_slices": 4,
      "slices": {
        "large(50-70%)": {
          "count": 14,
          "ratio": 0.004433185560481318,
          "models": {
            "CPL_Fusion": {
              "R@1,IoU=0.3": 0.5714285714285714,
              "R@1,IoU=0.5": 0.42857142857142855,
              "R@1,IoU=0.7": 0.0,
              "mIoU": 0.3226491923681906,
              "count": 14,
              "R@5,mIoU": 0.6310067783872091,
              "R@5,IoU=0.3": 1.0,
              "R@5,IoU=0.5": 1.0,
              "R@5,IoU=0.7": 0.0
            },
            "CPL_DMVS": {
              "R@1,IoU=0.3": 0.7857142857142857,
              "R@1,IoU=0.5": 0.5,
              "R@1,IoU=0.7": 0.0,
              "mIoU": 0.47977602611613696,
              "count": 14,
              "R@5,mIoU": 0.6861500896528483,
              "R@5,IoU=0.3": 1.0,
              "R@5,IoU=0.5": 1.0,
              "R@5,IoU=0.7": 0.07142857142857142
            }
          }
        },
        "medium(30-50%)": {
          "count": 1068,
          "ratio": 0.3381887270424319,
          "models": {
            "CPL_Fusion": {
              "R@1,IoU=0.3": 0.6685393258426966,
              "R@1,IoU=0.5": 0.46629213483146065,
              "R@1,IoU=0.7": 0.11423220973782772,
              "mIoU": 0.4032039385088569,
              "count": 1068,
              "R@5,mIoU": 0.7582082908289478,
              "R@5,IoU=0.3": 1.0,
              "R@5,IoU=0.5": 0.9756554307116105,
              "R@5,IoU=0.7": 0.6928838951310862
            },
            "CPL_DMVS": {
              "R@1,IoU=0.3": 0.47752808988764045,
              "R@1,IoU=0.5": 0.34269662921348315,
              "R@1,IoU=0.7": 0.17790262172284643,
              "mIoU": 0.32902138256923197,
              "count": 1068,
              "R@5,mIoU": 0.7266946616710498,
              "R@5,IoU=0.3": 0.9906367041198502,
              "R@5,IoU=0.5": 0.9026217228464419,
              "R@5,IoU=0.7": 0.6816479400749064
            }
          }
        },
        "small(10-30%)": {
          "count": 2052,
          "ratio": 0.6497783407219759,
          "models": {
            "CPL_Fusion": {
              "R@1,IoU=0.3": 0.33528265107212474,
              "R@1,IoU=0.5": 0.18031189083820662,
              "R@1,IoU=0.7": 0.0638401559454191,
              "mIoU": 0.2280689491837525,
              "count": 2052,
              "R@5,mIoU": 0.6079197540493139,
              "R@5,IoU=0.3": 0.9556530214424951,
              "R@5,IoU=0.5": 0.7509746588693957,
              "R@5,IoU=0.7": 0.31140350877192985
            },
            "CPL_DMVS": {
              "R@1,IoU=0.3": 0.32651072124756336,
              "R@1,IoU=0.5": 0.1949317738791423,
              "R@1,IoU=0.7": 0.06189083820662768,
              "mIoU": 0.20764403814504456,
              "count": 2052,
              "R@5,mIoU": 0.5503164395003916,
              "R@5,IoU=0.3": 0.8737816764132553,
              "R@5,IoU=0.5": 0.645224171539961,
              "R@5,IoU=0.7": 0.26072124756335285
            }
          }
        },
        "tiny(<=10%)": {
          "count": 24,
          "ratio": 0.007599746675110829,
          "models": {
            "CPL_Fusion": {
              "R@1,IoU=0.3": 0.0,
              "R@1,IoU=0.5": 0.0,
              "R@1,IoU=0.7": 0.0,
              "mIoU": 0.0,
              "count": 24,
              "R@5,mIoU": 0.20076359506397642,
              "R@5,IoU=0.3": 0.041666666666666664,
              "R@5,IoU=0.5": 0.0,
              "R@5,IoU=0.7": 0.0
            },
            "CPL_DMVS": {
              "R@1,IoU=0.3": 0.08333333333333333,
              "R@1,IoU=0.5": 0.0,
              "R@1,IoU=0.7": 0.0,
              "mIoU": 0.03901157259535667,
              "count": 24,
              "R@5,mIoU": 0.14082116656985758,
              "R@5,IoU=0.3": 0.25,
              "R@5,IoU=0.5": 0.0,
              "R@5,IoU=0.7": 0.0
            }
          }
        }
      }
    },
    "gt_position_bucket": {
      "dimension": "gt_position_bucket",
      "num_slices": 3,
      "slices": {
        "beginning": {
          "count": 1595,
          "ratio": 0.5050664977834072,
          "models": {
            "CPL_Fusion": {
              "R@1,IoU=0.3": 0.5786833855799373,
              "R@1,IoU=0.5": 0.361128526645768,
              "R@1,IoU=0.7": 0.10407523510971786,
              "mIoU": 0.36451541255635483,
              "count": 1595,
              "R@5,mIoU": 0.6598975273510649,
              "R@5,IoU=0.3": 0.9529780564263323,
              "R@5,IoU=0.5": 0.8012539184952978,
              "R@5,IoU=0.7": 0.4702194357366771
            },
            "CPL_DMVS": {
              "R@1,IoU=0.3": 0.2589341692789969,
              "R@1,IoU=0.5": 0.16426332288401255,
              "R@1,IoU=0.7": 0.07836990595611286,
              "mIoU": 0.17542785786959494,
              "count": 1595,
              "R@5,mIoU": 0.5524770168495313,
              "R@5,IoU=0.3": 0.8326018808777429,
              "R@5,IoU=0.5": 0.6200626959247649,
              "R@5,IoU=0.7": 0.3341692789968652
            }
          }
        },
        "end": {
          "count": 565,
          "ratio": 0.17891070297656744,
          "models": {
            "CPL_Fusion": {
              "R@1,IoU=0.3": 0.12212389380530973,
              "R@1,IoU=0.5": 0.09557522123893805,
              "R@1,IoU=0.7": 0.05309734513274336,
              "mIoU": 0.08159187075619552,
              "count": 565,
              "R@5,mIoU": 0.6313889146259464,
              "R@5,IoU=0.3": 0.9362831858407079,
              "R@5,IoU=0.5": 0.7858407079646018,
              "R@5,IoU=0.7": 0.41061946902654867
            },
            "CPL_DMVS": {
              "R@1,IoU=0.3": 0.536283185840708,
              "R@1,IoU=0.5": 0.368141592920354,
              "R@1,IoU=0.7": 0.16106194690265488,
              "mIoU": 0.3455577017487272,
              "count": 565,
              "R@5,mIoU": 0.6568862138624832,
              "R@5,IoU=0.3": 0.9734513274336283,
              "R@5,IoU=0.5": 0.8141592920353983,
              "R@5,IoU=0.7": 0.46017699115044247
            }
          }
        },
        "middle": {
          "count": 998,
          "ratio": 0.31602279924002535,
          "models": {
            "CPL_Fusion": {
              "R@1,IoU=0.3": 0.4188376753507014,
              "R@1,IoU=0.5": 0.24448897795591182,
              "R@1,IoU=0.7": 0.05711422845691383,
              "mIoU": 0.27618726326757265,
              "count": 998,
              "R@5,mIoU": 0.6629247677403376,
              "R@5,IoU=0.3": 0.996993987975952,
              "R@5,IoU=0.5": 0.8767535070140281,
              "R@5,IoU=0.7": 0.39779559118236474
            },
            "CPL_DMVS": {
              "R@1,IoU=0.3": 0.4779559118236473,
              "R@1,IoU=0.5": 0.30360721442885774,
              "R@1,IoU=0.7": 0.10120240480961924,
              "mIoU": 0.3107074250255019,
              "count": 998,
              "R@5,mIoU": 0.6673381653957872,
              "R@5,IoU=0.3": 0.9949899799599199,
              "R@5,IoU=0.5": 0.8547094188376754,
              "R@5,IoU=0.7": 0.47194388777555113
            }
          }
        }
      }
    },
    "video_length_bucket": {
      "dimension": "video_length_bucket",
      "num_slices": 3,
      "slices": {
        "medium(40-80s)": {
          "count": 199,
          "ratio": 0.0630145661811273,
          "models": {
            "CPL_Fusion": {
              "R@1,IoU=0.3": 0.3316582914572864,
              "R@1,IoU=0.5": 0.1658291457286432,
              "R@1,IoU=0.7": 0.035175879396984924,
              "mIoU": 0.19554749633494653,
              "count": 199,
              "R@5,mIoU": 0.5864490281505303,
              "R@5,IoU=0.3": 0.9296482412060302,
              "R@5,IoU=0.5": 0.6180904522613065,
              "R@5,IoU=0.7": 0.3015075376884422
            },
            "CPL_DMVS": {
              "R@1,IoU=0.3": 0.35678391959798994,
              "R@1,IoU=0.5": 0.1708542713567839,
              "R@1,IoU=0.7": 0.07537688442211055,
              "mIoU": 0.21755672312551824,
              "count": 199,
              "R@5,mIoU": 0.5481784923391608,
              "R@5,IoU=0.3": 0.914572864321608,
              "R@5,IoU=0.5": 0.5477386934673367,
              "R@5,IoU=0.7": 0.3015075376884422
            }
          }
        },
        "short(20-40s)": {
          "count": 2608,
          "ratio": 0.8258391386953768,
          "models": {
            "CPL_Fusion": {
              "R@1,IoU=0.3": 0.43328220858895705,
              "R@1,IoU=0.5": 0.2661042944785276,
              "R@1,IoU=0.7": 0.08128834355828221,
              "mIoU": 0.2799700784465446,
              "count": 2608,
              "R@5,mIoU": 0.6485184721900757,
              "R@5,IoU=0.3": 0.9616564417177914,
              "R@5,IoU=0.5": 0.8201687116564417,
              "R@5,IoU=0.7": 0.4217791411042945
            },
            "CPL_DMVS": {
              "R@1,IoU=0.3": 0.3692484662576687,
              "R@1,IoU=0.5": 0.2361963190184049,
              "R@1,IoU=0.7": 0.09087423312883436,
              "mIoU": 0.24118136737030066,
              "count": 2608,
              "R@5,mIoU": 0.5970672271520099,
              "R@5,IoU=0.3": 0.9029907975460123,
              "R@5,IoU=0.5": 0.7216257668711656,
              "R@5,IoU=0.7": 0.37193251533742333
            }
          }
        },
        "very_short(<=20s)": {
          "count": 351,
          "ratio": 0.11114629512349589,
          "models": {
            "CPL_Fusion": {
              "R@1,IoU=0.3": 0.6096866096866097,
              "R@1,IoU=0.5": 0.4188034188034188,
              "R@1,IoU=0.7": 0.09686609686609686,
              "mIoU": 0.3819386392775823,
              "count": 351,
              "R@5,mIoU": 0.7488053533327405,
              "R@5,IoU=0.3": 1.0,
              "R@5,IoU=0.5": 0.9544159544159544,
              "R@5,IoU=0.7": 0.6239316239316239
            },
            "CPL_DMVS": {
              "R@1,IoU=0.3": 0.452991452991453,
              "R@1,IoU=0.5": 0.3504273504273504,
              "R@1,IoU=0.7": 0.18518518518518517,
              "mIoU": 0.3214779229679871,
              "count": 351,
              "R@5,mIoU": 0.7182512632033218,
              "R@5,IoU=0.3": 0.9515669515669516,
              "R@5,IoU=0.5": 0.886039886039886,
              "R@5,IoU=0.7": 0.6666666666666666
            }
          }
        }
      }
    },
    "gt_length_bucket": {
      "dimension": "gt_length_bucket",
      "num_slices": 4,
      "slices": {
        "long(20-60s)": {
          "count": 3,
          "ratio": 0.0009499683343888537,
          "models": {
            "CPL_Fusion": {
              "R@1,IoU=0.3": 0.6666666666666666,
              "R@1,IoU=0.5": 0.6666666666666666,
              "R@1,IoU=0.7": 0.0,
              "mIoU": 0.44191653788628077,
              "count": 3,
              "R@5,mIoU": 0.6885801196466804,
              "R@5,IoU=0.3": 1.0,
              "R@5,IoU=0.5": 1.0,
              "R@5,IoU=0.7": 0.6666666666666666
            },
            "CPL_DMVS": {
              "R@1,IoU=0.3": 0.6666666666666666,
              "R@1,IoU=0.5": 0.0,
              "R@1,IoU=0.7": 0.0,
              "mIoU": 0.338794319503749,
              "count": 3,
              "R@5,mIoU": 0.7657055408725877,
              "R@5,IoU=0.3": 1.0,
              "R@5,IoU=0.5": 1.0,
              "R@5,IoU=0.7": 1.0
            }
          }
        },
        "medium(8-20s)": {
          "count": 1182,
          "ratio": 0.3742875237492084,
          "models": {
            "CPL_Fusion": {
              "R@1,IoU=0.3": 0.5896785109983079,
              "R@1,IoU=0.5": 0.39509306260575294,
              "R@1,IoU=0.7": 0.12267343485617598,
              "mIoU": 0.3684697048709836,
              "count": 1182,
              "R@5,mIoU": 0.7480685136102692,
              "R@5,IoU=0.3": 0.994077834179357,
              "R@5,IoU=0.5": 0.9585448392554992,
              "R@5,IoU=0.7": 0.6759729272419628
            },
            "CPL_DMVS": {
              "R@1,IoU=0.3": 0.44247038917089676,
              "R@1,IoU=0.5": 0.30372250423011843,
              "R@1,IoU=0.7": 0.1548223350253807,
              "mIoU": 0.3024360897908318,
              "count": 1182,
              "R@5,mIoU": 0.7064038002726726,
              "R@5,IoU=0.3": 0.9746192893401016,
              "R@5,IoU=0.5": 0.8747884940778342,
              "R@5,IoU=0.7": 0.6336717428087987
            }
          }
        },
        "short(3-8s)": {
          "count": 1959,
          "ratio": 0.6203293223559214,
          "models": {
            "CPL_Fusion": {
              "R@1,IoU=0.3": 0.3624298111281266,
              "R@1,IoU=0.5": 0.20673813169984687,
              "R@1,IoU=0.7": 0.055130168453292494,
              "mIoU": 0.23783469968447699,
              "count": 1959,
              "R@5,mIoU": 0.602837825041507,
              "R@5,IoU=0.3": 0.9509954058192955,
              "R@5,IoU=0.5": 0.74527820316488,
              "R@5,IoU=0.7": 0.2945380296069423
            },
            "CPL_DMVS": {
              "R@1,IoU=0.3": 0.3409903011740684,
              "R@1,IoU=0.5": 0.2113323124042879,
              "R@1,IoU=0.7": 0.06840224604389995,
              "mIoU": 0.21778341188065914,
              "count": 1959,
              "R@5,mIoU": 0.5508866605296339,
              "R@5,IoU=0.3": 0.8739152628892292,
              "R@5,IoU=0.5": 0.6457376212353242,
              "R@5,IoU=0.7": 0.2613578356304237
            }
          }
        },
        "very_short(<=3s)": {
          "count": 14,
          "ratio": 0.004433185560481318,
          "models": {
            "CPL_Fusion": {
              "R@1,IoU=0.3": 0.07142857142857142,
              "R@1,IoU=0.5": 0.0,
              "R@1,IoU=0.7": 0.0,
              "mIoU": 0.025804378044431253,
              "count": 14,
              "R@5,mIoU": 0.2591563136339055,
              "R@5,IoU=0.3": 0.21428571428571427,
              "R@5,IoU=0.5": 0.07142857142857142,
              "R@5,IoU=0.7": 0.07142857142857142
            },
            "CPL_DMVS": {
              "R@1,IoU=0.3": 0.0,
              "R@1,IoU=0.5": 0.0,
              "R@1,IoU=0.7": 0.0,
              "mIoU": 0.0,
              "count": 14,
              "R@5,mIoU": 0.1351189464165306,
              "R@5,IoU=0.3": 0.2857142857142857,
              "R@5,IoU=0.5": 0.0,
              "R@5,IoU=0.7": 0.0
            }
          }
        }
      }
    },
    "starts_at_beginning": {
      "dimension": "starts_at_beginning",
      "num_slices": 2,
      "slices": {
        "False": {
          "count": 2201,
          "ratio": 0.6969601013299557,
          "models": {
            "CPL_Fusion": {
              "R@1,IoU=0.3": 0.4357110404361654,
              "R@1,IoU=0.5": 0.28441617446615175,
              "R@1,IoU=0.7": 0.11358473421172194,
              "mIoU": 0.28638964732983674,
              "count": 2201,
              "R@5,mIoU": 0.6501472378228691,
              "R@5,IoU=0.3": 0.9763743752839619,
              "R@5,IoU=0.5": 0.8364379827351204,
              "R@5,IoU=0.7": 0.40299863698318944
            },
            "CPL_DMVS": {
              "R@1,IoU=0.3": 0.43752839618355294,
              "R@1,IoU=0.5": 0.275329395729214,
              "R@1,IoU=0.7": 0.10540663334847797,
              "mIoU": 0.28194540720386746,
              "count": 2201,
              "R@5,mIoU": 0.6291336850085295,
              "R@5,IoU=0.3": 0.959563834620627,
              "R@5,IoU=0.5": 0.7701044979554748,
              "R@5,IoU=0.7": 0.40299863698318944
            }
          }
        },
        "True": {
          "count": 957,
          "ratio": 0.3030398986700443,
          "models": {
            "CPL_Fusion": {
              "R@1,IoU=0.3": 0.47126436781609193,
              "R@1,IoU=0.5": 0.25914315569487983,
              "R@1,IoU=0.7": 0.003134796238244514,
              "mIoU": 0.28504991115225004,
              "count": 957,
              "R@5,mIoU": 0.6686480048540544,
              "R@5,IoU=0.3": 0.93521421107628,
              "R@5,IoU=0.5": 0.7899686520376176,
              "R@5,IoU=0.7": 0.5141065830721003
            },
            "CPL_DMVS": {
              "R@1,IoU=0.3": 0.24033437826541273,
              "R@1,IoU=0.5": 0.17450365726227796,
              "R@1,IoU=0.7": 0.08881922675026123,
              "mIoU": 0.1719662525702962,
              "count": 957,
              "R@5,mIoU": 0.5575985382116274,
              "R@5,IoU=0.3": 0.7931034482758621,
              "R@5,IoU=0.5": 0.6342737722048067,
              "R@5,IoU=0.7": 0.3939393939393939
            }
          }
        }
      }
    },
    "ends_at_end": {
      "dimension": "ends_at_end",
      "num_slices": 2,
      "slices": {
        "False": {
          "count": 3055,
          "ratio": 0.9673844205193161,
          "models": {
            "CPL_Fusion": {
              "R@1,IoU=0.3": 0.4582651391162029,
              "R@1,IoU=0.5": 0.28379705400981997,
              "R@1,IoU=0.7": 0.08248772504091653,
              "mIoU": 0.2935635174679586,
              "count": 3055,
              "R@5,mIoU": 0.6595437222612136,
              "R@5,IoU=0.3": 0.96759410801964,
              "R@5,IoU=0.5": 0.8274959083469722,
              "R@5,IoU=0.7": 0.4432078559738134
            },
            "CPL_DMVS": {
              "R@1,IoU=0.3": 0.37381342062193124,
              "R@1,IoU=0.5": 0.2392798690671031,
              "R@1,IoU=0.7": 0.09590834697217676,
              "mIoU": 0.24500435642724516,
              "count": 3055,
              "R@5,mIoU": 0.6051954202339666,
              "R@5,IoU=0.3": 0.9083469721767594,
              "R@5,IoU=0.5": 0.7250409165302782,
              "R@5,IoU=0.7": 0.3934533551554828
            }
          }
        },
        "True": {
          "count": 103,
          "ratio": 0.03261557948068398,
          "models": {
            "CPL_Fusion": {
              "R@1,IoU=0.3": 0.0970873786407767,
              "R@1,IoU=0.5": 0.06796116504854369,
              "R@1,IoU=0.7": 0.009708737864077669,
              "mIoU": 0.06116342602971257,
              "count": 103,
              "R@5,mIoU": 0.5433411610238575,
              "R@5,IoU=0.3": 0.8543689320388349,
              "R@5,IoU=0.5": 0.6699029126213593,
              "R@5,IoU=0.7": 0.24271844660194175
            },
            "CPL_DMVS": {
              "R@1,IoU=0.3": 0.49514563106796117,
              "R@1,IoU=0.5": 0.4077669902912621,
              "R@1,IoU=0.7": 0.23300970873786409,
              "mIoU": 0.3557789910704037,
              "count": 103,
              "R@5,mIoU": 0.674495465607116,
              "R@5,IoU=0.3": 0.9320388349514563,
              "R@5,IoU=0.5": 0.8446601941747572,
              "R@5,IoU=0.7": 0.6019417475728155
            }
          }
        }
      }
    },
    "query_density_bucket": {
      "dimension": "query_density_bucket",
      "num_slices": 4,
      "slices": {
        "dense(7+)": {
          "count": 262,
          "ratio": 0.08296390120329322,
          "models": {
            "CPL_Fusion": {
              "R@1,IoU=0.3": 0.4351145038167939,
              "R@1,IoU=0.5": 0.2786259541984733,
              "R@1,IoU=0.7": 0.0916030534351145,
              "mIoU": 0.2741966030661115,
              "count": 262,
              "R@5,mIoU": 0.6462681266661127,
              "R@5,IoU=0.3": 0.9541984732824428,
              "R@5,IoU=0.5": 0.8053435114503816,
              "R@5,IoU=0.7": 0.4732824427480916
            },
            "CPL_DMVS": {
              "R@1,IoU=0.3": 0.366412213740458,
              "R@1,IoU=0.5": 0.21374045801526717,
              "R@1,IoU=0.7": 0.09541984732824428,
              "mIoU": 0.24027712461861625,
              "count": 262,
              "R@5,mIoU": 0.5973183456926173,
              "R@5,IoU=0.3": 0.9045801526717557,
              "R@5,IoU=0.5": 0.7290076335877863,
              "R@5,IoU=0.7": 0.36259541984732824
            }
          }
        },
        "medium(4-6)": {
          "count": 1211,
          "ratio": 0.38347055098163396,
          "models": {
            "CPL_Fusion": {
              "R@1,IoU=0.3": 0.4475639966969447,
              "R@1,IoU=0.5": 0.27663088356729976,
              "R@1,IoU=0.7": 0.07431874483897605,
              "mIoU": 0.2862820331260352,
              "count": 1211,
              "R@5,mIoU": 0.6516522055426227,
              "R@5,IoU=0.3": 0.9603633360858794,
              "R@5,IoU=0.5": 0.8257638315441783,
              "R@5,IoU=0.7": 0.42609413707679605
            },
            "CPL_DMVS": {
              "R@1,IoU=0.3": 0.37241948802642444,
              "R@1,IoU=0.5": 0.24525185796862098,
              "R@1,IoU=0.7": 0.09083402146985962,
              "mIoU": 0.24465088227247853,
              "count": 1211,
              "R@5,mIoU": 0.615440754793177,
              "R@5,IoU=0.3": 0.9149463253509497,
              "R@5,IoU=0.5": 0.7456647398843931,
              "R@5,IoU=0.7": 0.40957886044591246
            }
          }
        },
        "single_query": {
          "count": 404,
          "ratio": 0.1279290690310323,
          "models": {
            "CPL_Fusion": {
              "R@1,IoU=0.3": 0.47277227722772275,
              "R@1,IoU=0.5": 0.27970297029702973,
              "R@1,IoU=0.7": 0.09653465346534654,
              "mIoU": 0.30138958590013615,
              "count": 404,
              "R@5,mIoU": 0.6583498321434601,
              "R@5,IoU=0.3": 0.9653465346534653,
              "R@5,IoU=0.5": 0.8118811881188119,
              "R@5,IoU=0.7": 0.452970297029703
            },
            "CPL_DMVS": {
              "R@1,IoU=0.3": 0.3613861386138614,
              "R@1,IoU=0.5": 0.2400990099009901,
              "R@1,IoU=0.7": 0.10148514851485149,
              "mIoU": 0.24451501965462163,
              "count": 404,
              "R@5,mIoU": 0.612217931680332,
              "R@5,IoU=0.3": 0.9158415841584159,
              "R@5,IoU=0.5": 0.7376237623762376,
              "R@5,IoU=0.7": 0.4084158415841584
            }
          }
        },
        "sparse(2-3)": {
          "count": 1281,
          "ratio": 0.4056364787840405,
          "models": {
            "CPL_Fusion": {
              "R@1,IoU=0.3": 0.43950039032006244,
              "R@1,IoU=0.5": 0.2755659640905542,
              "R@1,IoU=0.7": 0.078064012490242,
              "mIoU": 0.28325365645828976,
              "count": 1281,
              "R@5,mIoU": 0.6607523878289379,
              "R@5,IoU=0.3": 0.9687743950039032,
              "R@5,IoU=0.5": 0.8259172521467604,
              "R@5,IoU=0.7": 0.4340359094457455
            },
            "CPL_DMVS": {
              "R@1,IoU=0.3": 0.39032006245121,
              "R@1,IoU=0.5": 0.25214676034348166,
              "R@1,IoU=0.7": 0.11007025761124122,
              "mIoU": 0.2553666291514204,
              "count": 1281,
              "R@5,mIoU": 0.6004784049550693,
              "R@5,IoU=0.3": 0.9024199843871975,
              "R@5,IoU=0.5": 0.7103825136612022,
              "R@5,IoU=0.7": 0.39656518345042935
            }
          }
        }
      }
    },
    "has_overlapping_queries": {
      "dimension": "has_overlapping_queries",
      "num_slices": 2,
      "slices": {
        "False": {
          "count": 653,
          "ratio": 0.20677644078530716,
          "models": {
            "CPL_Fusion": {
              "R@1,IoU=0.3": 0.42879019908116384,
              "R@1,IoU=0.5": 0.26033690658499237,
              "R@1,IoU=0.7": 0.09188361408882083,
              "mIoU": 0.27615431143182223,
              "count": 653,
              "R@5,mIoU": 0.6481235174221393,
              "R@5,IoU=0.3": 0.9555895865237366,
              "R@5,IoU=0.5": 0.7993874425727412,
              "R@5,IoU=0.7": 0.42879019908116384
            },
            "CPL_DMVS": {
              "R@1,IoU=0.3": 0.3767228177641654,
              "R@1,IoU=0.5": 0.23736600306278713,
              "R@1,IoU=0.7": 0.10872894333843798,
              "mIoU": 0.2492525741406192,
              "count": 653,
              "R@5,mIoU": 0.6093099831757657,
              "R@5,IoU=0.3": 0.9157733537519143,
              "R@5,IoU=0.5": 0.7366003062787136,
              "R@5,IoU=0.7": 0.40428790199081166
            }
          }
        },
        "True": {
          "count": 2505,
          "ratio": 0.7932235592146929,
          "models": {
            "CPL_Fusion": {
              "R@1,IoU=0.3": 0.45109780439121755,
              "R@1,IoU=0.5": 0.2810379241516966,
              "R@1,IoU=0.7": 0.07704590818363273,
              "mIoU": 0.2885459534453868,
              "count": 2505,
              "R@5,mIoU": 0.6577427362142947,
              "R@5,IoU=0.3": 0.9660678642714571,
              "R@5,IoU=0.5": 0.8283433133732535,
              "R@5,IoU=0.7": 0.43872255489021955
            },
            "CPL_DMVS": {
              "R@1,IoU=0.3": 0.3780439121756487,
              "R@1,IoU=0.5": 0.2467065868263473,
              "R@1,IoU=0.7": 0.09820359281437126,
              "mIoU": 0.2484517421363917,
              "count": 2505,
              "R@5,mIoU": 0.6069723044944215,
              "R@5,IoU=0.3": 0.9073852295409182,
              "R@5,IoU=0.5": 0.7269461077844311,
              "R@5,IoU=0.7": 0.3992015968063872
            }
          }
        }
      }
    }
  },
  "divergences": [
    {
      "dimension": "ends_at_end",
      "slice": "True",
      "count": 103,
      "metric": "R@1,IoU=0.5",
      "max_diff": 0.3398058252427184,
      "best_model": "CPL_DMVS",
      "worst_model": "CPL_Fusion",
      "model_values": {
        "CPL_Fusion": 0.06796116504854369,
        "CPL_DMVS": 0.4077669902912621
      }
    },
    {
      "dimension": "gt_position_bucket",
      "slice": "end",
      "count": 565,
      "metric": "R@1,IoU=0.5",
      "max_diff": 0.27256637168141595,
      "best_model": "CPL_DMVS",
      "worst_model": "CPL_Fusion",
      "model_values": {
        "CPL_Fusion": 0.09557522123893805,
        "CPL_DMVS": 0.368141592920354
      }
    },
    {
      "dimension": "gt_position_bucket",
      "slice": "beginning",
      "count": 1595,
      "metric": "R@1,IoU=0.5",
      "max_diff": 0.19686520376175545,
      "best_model": "CPL_Fusion",
      "worst_model": "CPL_DMVS",
      "model_values": {
        "CPL_Fusion": 0.361128526645768,
        "CPL_DMVS": 0.16426332288401255
      }
    },
    {
      "dimension": "action_category",
      "slice": "interaction,perception",
      "count": 56,
      "metric": "R@1,IoU=0.5",
      "max_diff": 0.16071428571428573,
      "best_model": "CPL_Fusion",
      "worst_model": "CPL_DMVS",
      "model_values": {
        "CPL_Fusion": 0.375,
        "CPL_DMVS": 0.21428571428571427
      }
    },
    {
      "dimension": "action_category",
      "slice": "movement",
      "count": 325,
      "metric": "R@1,IoU=0.5",
      "max_diff": 0.13538461538461538,
      "best_model": "CPL_DMVS",
      "worst_model": "CPL_Fusion",
      "model_values": {
        "CPL_Fusion": 0.24615384615384617,
        "CPL_DMVS": 0.38153846153846155
      }
    },
    {
      "dimension": "gt_coverage_bucket",
      "slice": "medium(30-50%)",
      "count": 1068,
      "metric": "R@1,IoU=0.5",
      "max_diff": 0.1235955056179775,
      "best_model": "CPL_Fusion",
      "worst_model": "CPL_DMVS",
      "model_values": {
        "CPL_Fusion": 0.46629213483146065,
        "CPL_DMVS": 0.34269662921348315
      }
    },
    {
      "dimension": "action_category",
      "slice": "perception",
      "count": 496,
      "metric": "R@1,IoU=0.5",
      "max_diff": 0.12298387096774194,
      "best_model": "CPL_Fusion",
      "worst_model": "CPL_DMVS",
      "model_values": {
        "CPL_Fusion": 0.37701612903225806,
        "CPL_DMVS": 0.2540322580645161
      }
    },
    {
      "dimension": "action_category",
      "slice": "interaction,state_change",
      "count": 49,
      "metric": "R@1,IoU=0.5",
      "max_diff": 0.12244897959183673,
      "best_model": "CPL_DMVS",
      "worst_model": "CPL_Fusion",
      "model_values": {
        "CPL_Fusion": 0.1836734693877551,
        "CPL_DMVS": 0.30612244897959184
      }
    },
    {
      "dimension": "gt_length_bucket",
      "slice": "medium(8-20s)",
      "count": 1182,
      "metric": "R@1,IoU=0.5",
      "max_diff": 0.09137055837563451,
      "best_model": "CPL_Fusion",
      "worst_model": "CPL_DMVS",
      "model_values": {
        "CPL_Fusion": 0.39509306260575294,
        "CPL_DMVS": 0.30372250423011843
      }
    },
    {
      "dimension": "starts_at_beginning",
      "slice": "True",
      "count": 957,
      "metric": "R@1,IoU=0.5",
      "max_diff": 0.08463949843260188,
      "best_model": "CPL_Fusion",
      "worst_model": "CPL_DMVS",
      "model_values": {
        "CPL_Fusion": 0.25914315569487983,
        "CPL_DMVS": 0.17450365726227796
      }
    },
    {
      "dimension": "action_category",
      "slice": "interaction,movement",
      "count": 63,
      "metric": "R@1,IoU=0.5",
      "max_diff": 0.07936507936507936,
      "best_model": "CPL_Fusion",
      "worst_model": "CPL_DMVS",
      "model_values": {
        "CPL_Fusion": 0.38095238095238093,
        "CPL_DMVS": 0.30158730158730157
      }
    },
    {
      "dimension": "action_category",
      "slice": "movement,perception",
      "count": 76,
      "metric": "R@1,IoU=0.5",
      "max_diff": 0.07894736842105265,
      "best_model": "CPL_Fusion",
      "worst_model": "CPL_DMVS",
      "model_values": {
        "CPL_Fusion": 0.39473684210526316,
        "CPL_DMVS": 0.3157894736842105
      }
    },
    {
      "dimension": "has_temporal_cue",
      "slice": "True",
      "count": 107,
      "metric": "R@1,IoU=0.5",
      "max_diff": 0.07476635514018692,
      "best_model": "CPL_DMVS",
      "worst_model": "CPL_Fusion",
      "model_values": {
        "CPL_Fusion": 0.2803738317757009,
        "CPL_DMVS": 0.35514018691588783
      }
    },
    {
      "dimension": "video_length_bucket",
      "slice": "very_short(<=20s)",
      "count": 351,
      "metric": "R@1,IoU=0.5",
      "max_diff": 0.06837606837606841,
      "best_model": "CPL_Fusion",
      "worst_model": "CPL_DMVS",
      "model_values": {
        "CPL_Fusion": 0.4188034188034188,
        "CPL_DMVS": 0.3504273504273504
      }
    },
    {
      "dimension": "query_density_bucket",
      "slice": "dense(7+)",
      "count": 262,
      "metric": "R@1,IoU=0.5",
      "max_diff": 0.06488549618320613,
      "best_model": "CPL_Fusion",
      "worst_model": "CPL_DMVS",
      "model_values": {
        "CPL_Fusion": 0.2786259541984733,
        "CPL_DMVS": 0.21374045801526717
      }
    },
    {
      "dimension": "action_complexity",
      "slice": "no_verb",
      "count": 234,
      "metric": "R@1,IoU=0.5",
      "max_diff": 0.05982905982905984,
      "best_model": "CPL_Fusion",
      "worst_model": "CPL_DMVS",
      "model_values": {
        "CPL_Fusion": 0.32051282051282054,
        "CPL_DMVS": 0.2606837606837607
      }
    },
    {
      "dimension": "action_category",
      "slice": "unknown",
      "count": 234,
      "metric": "R@1,IoU=0.5",
      "max_diff": 0.05982905982905984,
      "best_model": "CPL_Fusion",
      "worst_model": "CPL_DMVS",
      "model_values": {
        "CPL_Fusion": 0.32051282051282054,
        "CPL_DMVS": 0.2606837606837607
      }
    },
    {
      "dimension": "gt_position_bucket",
      "slice": "middle",
      "count": 998,
      "metric": "R@1,IoU=0.5",
      "max_diff": 0.05911823647294592,
      "best_model": "CPL_DMVS",
      "worst_model": "CPL_Fusion",
      "model_values": {
        "CPL_Fusion": 0.24448897795591182,
        "CPL_DMVS": 0.30360721442885774
      }
    },
    {
      "dimension": "ends_at_end",
      "slice": "False",
      "count": 3055,
      "metric": "R@1,IoU=0.5",
      "max_diff": 0.044517184942716864,
      "best_model": "CPL_Fusion",
      "worst_model": "CPL_DMVS",
      "model_values": {
        "CPL_Fusion": 0.28379705400981997,
        "CPL_DMVS": 0.2392798690671031
      }
    },
    {
      "dimension": "query_length_bucket",
      "slice": "medium(6-10)",
      "count": 1914,
      "metric": "R@1,IoU=0.5",
      "max_diff": 0.04022988505747124,
      "best_model": "CPL_Fusion",
      "worst_model": "CPL_DMVS",
      "model_values": {
        "CPL_Fusion": 0.2800417972831766,
        "CPL_DMVS": 0.23981191222570533
      }
    },
    {
      "dimension": "query_density_bucket",
      "slice": "single_query",
      "count": 404,
      "metric": "R@1,IoU=0.5",
      "max_diff": 0.03960396039603964,
      "best_model": "CPL_Fusion",
      "worst_model": "CPL_DMVS",
      "model_values": {
        "CPL_Fusion": 0.27970297029702973,
        "CPL_DMVS": 0.2400990099009901
      }
    },
    {
      "dimension": "action_complexity",
      "slice": "dual_action",
      "count": 517,
      "metric": "R@1,IoU=0.5",
      "max_diff": 0.036750483558994185,
      "best_model": "CPL_Fusion",
      "worst_model": "CPL_DMVS",
      "model_values": {
        "CPL_Fusion": 0.2978723404255319,
        "CPL_DMVS": 0.2611218568665377
      }
    },
    {
      "dimension": "has_temporal_cue",
      "slice": "False",
      "count": 3051,
      "metric": "R@1,IoU=0.5",
      "max_diff": 0.03572599147820388,
      "best_model": "CPL_Fusion",
      "worst_model": "CPL_DMVS",
      "model_values": {
        "CPL_Fusion": 0.27663061291379876,
        "CPL_DMVS": 0.24090462143559488
      }
    },
    {
      "dimension": "has_overlapping_queries",
      "slice": "True",
      "count": 2505,
      "metric": "R@1,IoU=0.5",
      "max_diff": 0.03433133732534929,
      "best_model": "CPL_Fusion",
      "worst_model": "CPL_DMVS",
      "model_values": {
        "CPL_Fusion": 0.2810379241516966,
        "CPL_DMVS": 0.2467065868263473
      }
    },
    {
      "dimension": "has_person_subject",
      "slice": "True",
      "count": 3155,
      "metric": "R@1,IoU=0.5",
      "max_diff": 0.032012678288431046,
      "best_model": "CPL_Fusion",
      "worst_model": "CPL_DMVS",
      "model_values": {
        "CPL_Fusion": 0.27702060221870045,
        "CPL_DMVS": 0.2450079239302694
      }
    },
    {
      "dimension": "query_density_bucket",
      "slice": "medium(4-6)",
      "count": 1211,
      "metric": "R@1,IoU=0.5",
      "max_diff": 0.03137902559867878,
      "best_model": "CPL_Fusion",
      "worst_model": "CPL_DMVS",
      "model_values": {
        "CPL_Fusion": 0.27663088356729976,
        "CPL_DMVS": 0.24525185796862098
      }
    },
    {
      "dimension": "action_category",
      "slice": "state_change",
      "count": 807,
      "metric": "R@1,IoU=0.5",
      "max_diff": 0.03097893432465923,
      "best_model": "CPL_Fusion",
      "worst_model": "CPL_DMVS",
      "model_values": {
        "CPL_Fusion": 0.22304832713754646,
        "CPL_DMVS": 0.19206939281288724
      }
    },
    {
      "dimension": "action_category",
      "slice": "movement,state_change",
      "count": 33,
      "metric": "R@1,IoU=0.5",
      "max_diff": 0.030303030303030304,
      "best_model": "CPL_Fusion",
      "worst_model": "CPL_DMVS",
      "model_values": {
        "CPL_Fusion": 0.24242424242424243,
        "CPL_DMVS": 0.21212121212121213
      }
    },
    {
      "dimension": "video_length_bucket",
      "slice": "short(20-40s)",
      "count": 2608,
      "metric": "R@1,IoU=0.5",
      "max_diff": 0.02990797546012272,
      "best_model": "CPL_Fusion",
      "worst_model": "CPL_DMVS",
      "model_values": {
        "CPL_Fusion": 0.2661042944785276,
        "CPL_DMVS": 0.2361963190184049
      }
    },
    {
      "dimension": "action_complexity",
      "slice": "single_action",
      "count": 2381,
      "metric": "R@1,IoU=0.5",
      "max_diff": 0.02897942041159174,
      "best_model": "CPL_Fusion",
      "worst_model": "CPL_DMVS",
      "model_values": {
        "CPL_Fusion": 0.26711465770684584,
        "CPL_DMVS": 0.2381352372952541
      }
    }
  ],
  "strengths": {
    "CPL_Fusion": {
      "best_slices": [
        {
          "dimension": "gt_coverage_bucket",
          "slice": "medium(30-50%)",
          "count": 1068,
          "R@1,IoU=0.5": 0.46629213483146065
        },
        {
          "dimension": "video_length_bucket",
          "slice": "very_short(<=20s)",
          "count": 351,
          "R@1,IoU=0.5": 0.4188034188034188
        },
        {
          "dimension": "gt_length_bucket",
          "slice": "medium(8-20s)",
          "count": 1182,
          "R@1,IoU=0.5": 0.39509306260575294
        },
        {
          "dimension": "action_category",
          "slice": "movement,perception",
          "count": 76,
          "R@1,IoU=0.5": 0.39473684210526316
        },
        {
          "dimension": "action_category",
          "slice": "interaction,movement",
          "count": 63,
          "R@1,IoU=0.5": 0.38095238095238093
        },
        {
          "dimension": "action_category",
          "slice": "perception",
          "count": 496,
          "R@1,IoU=0.5": 0.37701612903225806
        },
        {
          "dimension": "action_category",
          "slice": "interaction,perception",
          "count": 56,
          "R@1,IoU=0.5": 0.375
        },
        {
          "dimension": "gt_position_bucket",
          "slice": "beginning",
          "count": 1595,
          "R@1,IoU=0.5": 0.361128526645768
        },
        {
          "dimension": "action_complexity",
          "slice": "no_verb",
          "count": 234,
          "R@1,IoU=0.5": 0.32051282051282054
        },
        {
          "dimension": "action_category",
          "slice": "unknown",
          "count": 234,
          "R@1,IoU=0.5": 0.32051282051282054
        }
      ],
      "worst_slices": [
        {
          "dimension": "ends_at_end",
          "slice": "True",
          "count": 103,
          "R@1,IoU=0.5": 0.06796116504854369
        },
        {
          "dimension": "gt_position_bucket",
          "slice": "end",
          "count": 565,
          "R@1,IoU=0.5": 0.09557522123893805
        },
        {
          "dimension": "video_length_bucket",
          "slice": "medium(40-80s)",
          "count": 199,
          "R@1,IoU=0.5": 0.1658291457286432
        },
        {
          "dimension": "gt_coverage_bucket",
          "slice": "small(10-30%)",
          "count": 2052,
          "R@1,IoU=0.5": 0.18031189083820662
        },
        {
          "dimension": "action_category",
          "slice": "interaction,state_change",
          "count": 49,
          "R@1,IoU=0.5": 0.1836734693877551
        },
        {
          "dimension": "gt_length_bucket",
          "slice": "short(3-8s)",
          "count": 1959,
          "R@1,IoU=0.5": 0.20673813169984687
        },
        {
          "dimension": "action_category",
          "slice": "perception,state_change",
          "count": 68,
          "R@1,IoU=0.5": 0.22058823529411764
        },
        {
          "dimension": "action_category",
          "slice": "state_change",
          "count": 807,
          "R@1,IoU=0.5": 0.22304832713754646
        },
        {
          "dimension": "action_category",
          "slice": "movement,state_change",
          "count": 33,
          "R@1,IoU=0.5": 0.24242424242424243
        },
        {
          "dimension": "gt_position_bucket",
          "slice": "middle",
          "count": 998,
          "R@1,IoU=0.5": 0.24448897795591182
        }
      ]
    },
    "CPL_DMVS": {
      "best_slices": [
        {
          "dimension": "ends_at_end",
          "slice": "True",
          "count": 103,
          "R@1,IoU=0.5": 0.4077669902912621
        },
        {
          "dimension": "action_category",
          "slice": "movement",
          "count": 325,
          "R@1,IoU=0.5": 0.38153846153846155
        },
        {
          "dimension": "gt_position_bucket",
          "slice": "end",
          "count": 565,
          "R@1,IoU=0.5": 0.368141592920354
        },
        {
          "dimension": "has_temporal_cue",
          "slice": "True",
          "count": 107,
          "R@1,IoU=0.5": 0.35514018691588783
        },
        {
          "dimension": "video_length_bucket",
          "slice": "very_short(<=20s)",
          "count": 351,
          "R@1,IoU=0.5": 0.3504273504273504
        },
        {
          "dimension": "gt_coverage_bucket",
          "slice": "medium(30-50%)",
          "count": 1068,
          "R@1,IoU=0.5": 0.34269662921348315
        },
        {
          "dimension": "action_category",
          "slice": "movement,perception",
          "count": 76,
          "R@1,IoU=0.5": 0.3157894736842105
        },
        {
          "dimension": "action_category",
          "slice": "interaction,state_change",
          "count": 49,
          "R@1,IoU=0.5": 0.30612244897959184
        },
        {
          "dimension": "gt_length_bucket",
          "slice": "medium(8-20s)",
          "count": 1182,
          "R@1,IoU=0.5": 0.30372250423011843
        },
        {
          "dimension": "gt_position_bucket",
          "slice": "middle",
          "count": 998,
          "R@1,IoU=0.5": 0.30360721442885774
        }
      ],
      "worst_slices": [
        {
          "dimension": "gt_position_bucket",
          "slice": "beginning",
          "count": 1595,
          "R@1,IoU=0.5": 0.16426332288401255
        },
        {
          "dimension": "video_length_bucket",
          "slice": "medium(40-80s)",
          "count": 199,
          "R@1,IoU=0.5": 0.1708542713567839
        },
        {
          "dimension": "starts_at_beginning",
          "slice": "True",
          "count": 957,
          "R@1,IoU=0.5": 0.17450365726227796
        },
        {
          "dimension": "action_category",
          "slice": "state_change",
          "count": 807,
          "R@1,IoU=0.5": 0.19206939281288724
        },
        {
          "dimension": "gt_coverage_bucket",
          "slice": "small(10-30%)",
          "count": 2052,
          "R@1,IoU=0.5": 0.1949317738791423
        },
        {
          "dimension": "action_category",
          "slice": "perception,state_change",
          "count": 68,
          "R@1,IoU=0.5": 0.20588235294117646
        },
        {
          "dimension": "gt_length_bucket",
          "slice": "short(3-8s)",
          "count": 1959,
          "R@1,IoU=0.5": 0.2113323124042879
        },
        {
          "dimension": "action_category",
          "slice": "movement,state_change",
          "count": 33,
          "R@1,IoU=0.5": 0.21212121212121213
        },
        {
          "dimension": "query_density_bucket",
          "slice": "dense(7+)",
          "count": 262,
          "R@1,IoU=0.5": 0.21374045801526717
        },
        {
          "dimension": "action_category",
          "slice": "interaction,perception",
          "count": 56,
          "R@1,IoU=0.5": 0.21428571428571427
        }
      ]
    }
  }
}