{
  "dataset": "charades",
  "model_names": [
    "CPL",
    "CPL_MoE",
    "CPL_DMVS"
  ],
  "num_samples": 3158,
  "iou_thresholds": [
    0.3,
    0.5,
    0.7
  ],
  "global_metrics_percent": {
    "CPL": {
      "R@1,IoU=0.3": 66.0545,
      "R@1,IoU=0.5": 47.7834,
      "R@1,IoU=0.7": 22.7676,
      "mIoU": 43.1875,
      "count": 3158
    },
    "CPL_MoE": {
      "R@1,IoU=0.3": 64.3445,
      "R@1,IoU=0.5": 46.2001,
      "R@1,IoU=0.7": 21.3743,
      "mIoU": 41.672,
      "count": 3158
    },
    "CPL_DMVS": {
      "R@1,IoU=0.3": 37.7771,
      "R@1,IoU=0.5": 24.4775,
      "R@1,IoU=0.7": 10.038,
      "mIoU": 24.8617,
      "count": 3158
    }
  },
  "dimension_summary": {
    "query_length_bucket": {
      "dimension": "query_length_bucket",
      "num_slices": 3,
      "slices": [
        {
          "slice": "medium(6-10)",
          "count": 1914,
          "ratio": 0.60608,
          "models_percent": {
            "CPL": {
              "R@1,IoU=0.3": 65.6217,
              "R@1,IoU=0.5": 47.4922,
              "R@1,IoU=0.7": 22.3093,
              "mIoU": 43.0215,
              "count": 1914,
              "R@5,mIoU": 66.7554,
              "R@5,IoU=0.3": 96.6562,
              "R@5,IoU=0.5": 82.3406,
              "R@5,IoU=0.7": 50.1567
            },
            "CPL_MoE": {
              "R@1,IoU=0.3": 63.7931,
              "R@1,IoU=0.5": 45.5068,
              "R@1,IoU=0.7": 21.7346,
              "mIoU": 41.4931,
              "count": 1914,
              "R@5,mIoU": 66.4567,
              "R@5,IoU=0.3": 97.2832,
              "R@5,IoU=0.5": 82.8109,
              "R@5,IoU=0.7": 49.2163
            },
            "CPL_DMVS": {
              "R@1,IoU=0.3": 37.0951,
              "R@1,IoU=0.5": 23.9812,
              "R@1,IoU=0.7": 9.8224,
              "mIoU": 24.3668,
              "count": 1914,
              "R@5,mIoU": 61.0741,
              "R@5,IoU=0.3": 90.8568,
              "R@5,IoU=0.5": 73.6677,
              "R@5,IoU=0.7": 40.7524
            }
          }
        },
        {
          "slice": "short(<=5)",
          "count": 1243,
          "ratio": 0.393604,
          "models_percent": {
            "CPL": {
              "R@1,IoU=0.3": 66.6935,
              "R@1,IoU=0.5": 48.1899,
              "R@1,IoU=0.7": 23.4916,
              "mIoU": 43.4354,
              "count": 1243,
              "R@5,mIoU": 66.443,
              "R@5,IoU=0.3": 97.3451,
              "R@5,IoU=0.5": 83.3467,
              "R@5,IoU=0.7": 48.9139
            },
            "CPL_MoE": {
              "R@1,IoU=0.3": 65.1649,
              "R@1,IoU=0.5": 47.2245,
              "R@1,IoU=0.7": 20.7562,
              "mIoU": 41.9092,
              "count": 1243,
              "R@5,mIoU": 66.0063,
              "R@5,IoU=0.3": 97.5865,
              "R@5,IoU=0.5": 83.4272,
              "R@5,IoU=0.7": 47.2245
            },
            "CPL_DMVS": {
              "R@1,IoU=0.3": 38.8576,
              "R@1,IoU=0.5": 25.2615,
              "R@1,IoU=0.7": 10.3781,
              "mIoU": 25.6298,
              "count": 1243,
              "R@5,mIoU": 60.2507,
              "R@5,IoU=0.3": 90.9895,
              "R@5,IoU=0.5": 71.7619,
              "R@5,IoU=0.7": 38.9381
            }
          }
        },
        {
          "slice": "long(11-15)",
          "count": 1,
          "ratio": 0.000317,
          "models_percent": {
            "CPL": {
              "R@1,IoU=0.3": 100.0,
              "R@1,IoU=0.5": 100.0,
              "R@1,IoU=0.7": 0.0,
              "mIoU": 52.9724,
              "count": 1,
              "R@5,mIoU": 92.6113,
              "R@5,IoU=0.3": 100.0,
              "R@5,IoU=0.5": 100.0,
              "R@5,IoU=0.7": 100.0
            },
            "CPL_MoE": {
              "R@1,IoU=0.3": 100.0,
              "R@1,IoU=0.5": 100.0,
              "R@1,IoU=0.7": 100.0,
              "mIoU": 89.4686,
              "count": 1,
              "R@5,mIoU": 89.4686,
              "R@5,IoU=0.3": 100.0,
              "R@5,IoU=0.5": 100.0,
              "R@5,IoU=0.7": 100.0
            },
            "CPL_DMVS": {
              "R@1,IoU=0.3": 0.0,
              "R@1,IoU=0.5": 0.0,
              "R@1,IoU=0.7": 0.0,
              "mIoU": 17.4615,
              "count": 1,
              "R@5,mIoU": 47.0908,
              "R@5,IoU=0.3": 100.0,
              "R@5,IoU=0.5": 0.0,
              "R@5,IoU=0.7": 0.0
            }
          }
        }
      ]
    },
    "action_complexity": {
      "dimension": "action_complexity",
      "num_slices": 4,
      "slices": [
        {
          "slice": "single_action",
          "count": 2381,
          "ratio": 0.753958,
          "models_percent": {
            "CPL": {
              "R@1,IoU=0.3": 66.2327,
              "R@1,IoU=0.5": 48.089,
              "R@1,IoU=0.7": 22.4276,
              "mIoU": 43.1519,
              "count": 2381,
              "R@5,mIoU": 66.317,
              "R@5,IoU=0.3": 96.9341,
              "R@5,IoU=0.5": 82.6123,
              "R@5,IoU=0.7": 48.509
            },
            "CPL_MoE": {
              "R@1,IoU=0.3": 64.8047,
              "R@1,IoU=0.5": 46.7451,
              "R@1,IoU=0.7": 21.2936,
              "mIoU": 41.868,
              "count": 2381,
              "R@5,mIoU": 65.9271,
              "R@5,IoU=0.3": 97.4381,
              "R@5,IoU=0.5": 82.6963,
              "R@5,IoU=0.7": 47.4171
            },
            "CPL_DMVS": {
              "R@1,IoU=0.3": 37.1273,
              "R@1,IoU=0.5": 23.8135,
              "R@1,IoU=0.7": 9.7018,
              "mIoU": 24.4403,
              "count": 2381,
              "R@5,mIoU": 60.3129,
              "R@5,IoU=0.3": 90.5502,
              "R@5,IoU=0.5": 72.3646,
              "R@5,IoU=0.7": 39.1012
            }
          }
        },
        {
          "slice": "dual_action",
          "count": 517,
          "ratio": 0.163711,
          "models_percent": {
            "CPL": {
              "R@1,IoU=0.3": 66.3443,
              "R@1,IoU=0.5": 45.8414,
              "R@1,IoU=0.7": 21.6634,
              "mIoU": 43.0847,
              "count": 517,
              "R@5,mIoU": 66.6658,
              "R@5,IoU=0.3": 96.7118,
              "R@5,IoU=0.5": 81.0445,
              "R@5,IoU=0.7": 50.2901
            },
            "CPL_MoE": {
              "R@1,IoU=0.3": 64.2166,
              "R@1,IoU=0.5": 43.1335,
              "R@1,IoU=0.7": 20.3095,
              "mIoU": 40.7415,
              "count": 517,
              "R@5,mIoU": 66.6811,
              "R@5,IoU=0.3": 97.4855,
              "R@5,IoU=0.5": 82.3985,
              "R@5,IoU=0.7": 48.5493
            },
            "CPL_DMVS": {
              "R@1,IoU=0.3": 41.1992,
              "R@1,IoU=0.5": 26.1122,
              "R@1,IoU=0.7": 9.8646,
              "mIoU": 26.0084,
              "count": 517,
              "R@5,mIoU": 61.3522,
              "R@5,IoU=0.3": 91.4894,
              "R@5,IoU=0.5": 72.9207,
              "R@5,IoU=0.7": 41.3926
            }
          }
        },
        {
          "slice": "no_verb",
          "count": 234,
          "ratio": 0.074098,
          "models_percent": {
            "CPL": {
              "R@1,IoU=0.3": 63.2479,
              "R@1,IoU=0.5": 49.1453,
              "R@1,IoU=0.7": 29.4872,
              "mIoU": 44.0535,
              "count": 234,
              "R@5,mIoU": 70.1168,
              "R@5,IoU=0.3": 97.4359,
              "R@5,IoU=0.5": 87.6068,
              "R@5,IoU=0.7": 61.1111
            },
            "CPL_MoE": {
              "R@1,IoU=0.3": 59.4017,
              "R@1,IoU=0.5": 47.0085,
              "R@1,IoU=0.7": 24.7863,
              "mIoU": 41.9109,
              "count": 234,
              "R@5,mIoU": 69.4492,
              "R@5,IoU=0.3": 97.0085,
              "R@5,IoU=0.5": 88.0342,
              "R@5,IoU=0.7": 59.4017
            },
            "CPL_DMVS": {
              "R@1,IoU=0.3": 35.4701,
              "R@1,IoU=0.5": 26.0684,
              "R@1,IoU=0.7": 14.5299,
              "mIoU": 26.1474,
              "count": 234,
              "R@5,mIoU": 64.0027,
              "R@5,IoU=0.3": 93.1624,
              "R@5,IoU=0.5": 78.6325,
              "R@5,IoU=0.7": 46.5812
            }
          }
        },
        {
          "slice": "multi_action(3+)",
          "count": 26,
          "ratio": 0.008233,
          "models_percent": {
            "CPL": {
              "R@1,IoU=0.3": 69.2308,
              "R@1,IoU=0.5": 46.1538,
              "R@1,IoU=0.7": 15.3846,
              "mIoU": 40.702,
              "count": 26,
              "R@5,mIoU": 64.4875,
              "R@5,IoU=0.3": 96.1538,
              "R@5,IoU=0.5": 84.6154,
              "R@5,IoU=0.7": 42.3077
            },
            "CPL_MoE": {
              "R@1,IoU=0.3": 69.2308,
              "R@1,IoU=0.5": 50.0,
              "R@1,IoU=0.7": 19.2308,
              "mIoU": 40.0814,
              "count": 26,
              "R@5,mIoU": 62.91,
              "R@5,IoU=0.3": 96.1538,
              "R@5,IoU=0.5": 84.6154,
              "R@5,IoU=0.7": 42.3077
            },
            "CPL_DMVS": {
              "R@1,IoU=0.3": 50.0,
              "R@1,IoU=0.5": 38.4615,
              "R@1,IoU=0.7": 3.8462,
              "mIoU": 29.0833,
              "count": 26,
              "R@5,mIoU": 58.988,
              "R@5,IoU=0.3": 92.3077,
              "R@5,IoU=0.5": 69.2308,
              "R@5,IoU=0.7": 38.4615
            }
          }
        }
      ]
    },
    "action_category": {
      "dimension": "action_category",
      "num_slices": 15,
      "slices": [
        {
          "slice": "interaction",
          "count": 945,
          "ratio": 0.29924,
          "models_percent": {
            "CPL": {
              "R@1,IoU=0.3": 63.4921,
              "R@1,IoU=0.5": 44.8677,
              "R@1,IoU=0.7": 17.9894,
              "mIoU": 40.8617,
              "count": 945,
              "R@5,mIoU": 65.4086,
              "R@5,IoU=0.3": 98.3069,
              "R@5,IoU=0.5": 82.1164,
              "R@5,IoU=0.7": 43.5979
            },
            "CPL_MoE": {
              "R@1,IoU=0.3": 63.1746,
              "R@1,IoU=0.5": 44.0212,
              "R@1,IoU=0.7": 16.2963,
              "mIoU": 39.8501,
              "count": 945,
              "R@5,mIoU": 65.1045,
              "R@5,IoU=0.3": 98.6243,
              "R@5,IoU=0.5": 82.4339,
              "R@5,IoU=0.7": 41.9048
            },
            "CPL_DMVS": {
              "R@1,IoU=0.3": 36.4021,
              "R@1,IoU=0.5": 22.7513,
              "R@1,IoU=0.7": 6.6667,
              "mIoU": 23.8374,
              "count": 945,
              "R@5,mIoU": 61.6783,
              "R@5,IoU=0.3": 93.8624,
              "R@5,IoU=0.5": 76.4021,
              "R@5,IoU=0.7": 36.4021
            }
          }
        },
        {
          "slice": "state_change",
          "count": 807,
          "ratio": 0.255541,
          "models_percent": {
            "CPL": {
              "R@1,IoU=0.3": 68.5254,
              "R@1,IoU=0.5": 47.2119,
              "R@1,IoU=0.7": 21.1896,
              "mIoU": 43.5613,
              "count": 807,
              "R@5,mIoU": 64.4104,
              "R@5,IoU=0.3": 96.1586,
              "R@5,IoU=0.5": 80.4213,
              "R@5,IoU=0.7": 44.114
            },
            "CPL_MoE": {
              "R@1,IoU=0.3": 67.2862,
              "R@1,IoU=0.5": 46.9641,
              "R@1,IoU=0.7": 17.72,
              "mIoU": 41.7975,
              "count": 807,
              "R@5,mIoU": 63.482,
              "R@5,IoU=0.3": 96.6543,
              "R@5,IoU=0.5": 80.1735,
              "R@5,IoU=0.7": 38.6617
            },
            "CPL_DMVS": {
              "R@1,IoU=0.3": 33.829,
              "R@1,IoU=0.5": 19.2069,
              "R@1,IoU=0.7": 7.5589,
              "mIoU": 21.1473,
              "count": 807,
              "R@5,mIoU": 54.7176,
              "R@5,IoU=0.3": 83.891,
              "R@5,IoU=0.5": 62.3296,
              "R@5,IoU=0.7": 32.7138
            }
          }
        },
        {
          "slice": "perception",
          "count": 496,
          "ratio": 0.157061,
          "models_percent": {
            "CPL": {
              "R@1,IoU=0.3": 65.9274,
              "R@1,IoU=0.5": 51.6129,
              "R@1,IoU=0.7": 29.0323,
              "mIoU": 44.8787,
              "count": 496,
              "R@5,mIoU": 69.5499,
              "R@5,IoU=0.3": 96.1694,
              "R@5,IoU=0.5": 84.6774,
              "R@5,IoU=0.7": 59.879
            },
            "CPL_MoE": {
              "R@1,IoU=0.3": 60.4839,
              "R@1,IoU=0.5": 46.7742,
              "R@1,IoU=0.7": 28.4274,
              "mIoU": 41.6243,
              "count": 496,
              "R@5,mIoU": 69.4798,
              "R@5,IoU=0.3": 96.9758,
              "R@5,IoU=0.5": 86.2903,
              "R@5,IoU=0.7": 63.9113
            },
            "CPL_DMVS": {
              "R@1,IoU=0.3": 37.9032,
              "R@1,IoU=0.5": 25.4032,
              "R@1,IoU=0.7": 12.2984,
              "mIoU": 25.6047,
              "count": 496,
              "R@5,mIoU": 63.5617,
              "R@5,IoU=0.3": 93.9516,
              "R@5,IoU=0.5": 75.6048,
              "R@5,IoU=0.7": 45.7661
            }
          }
        },
        {
          "slice": "movement",
          "count": 325,
          "ratio": 0.102913,
          "models_percent": {
            "CPL": {
              "R@1,IoU=0.3": 71.3846,
              "R@1,IoU=0.5": 54.4615,
              "R@1,IoU=0.7": 25.5385,
              "mIoU": 46.8926,
              "count": 325,
              "R@5,mIoU": 66.0766,
              "R@5,IoU=0.3": 95.0769,
              "R@5,IoU=0.5": 80.6154,
              "R@5,IoU=0.7": 48.9231
            },
            "CPL_MoE": {
              "R@1,IoU=0.3": 69.2308,
              "R@1,IoU=0.5": 50.4615,
              "R@1,IoU=0.7": 28.3077,
              "mIoU": 46.104,
              "count": 325,
              "R@5,mIoU": 65.9232,
              "R@5,IoU=0.3": 95.6923,
              "R@5,IoU=0.5": 78.7692,
              "R@5,IoU=0.7": 49.8462
            },
            "CPL_DMVS": {
              "R@1,IoU=0.3": 47.3846,
              "R@1,IoU=0.5": 38.1538,
              "R@1,IoU=0.7": 19.6923,
              "mIoU": 32.8175,
              "count": 325,
              "R@5,mIoU": 62.8294,
              "R@5,IoU=0.3": 90.4615,
              "R@5,IoU=0.5": 76.3077,
              "R@5,IoU=0.7": 48.0
            }
          }
        },
        {
          "slice": "unknown",
          "count": 234,
          "ratio": 0.074098,
          "models_percent": {
            "CPL": {
              "R@1,IoU=0.3": 63.2479,
              "R@1,IoU=0.5": 49.1453,
              "R@1,IoU=0.7": 29.4872,
              "mIoU": 44.0535,
              "count": 234,
              "R@5,mIoU": 70.1168,
              "R@5,IoU=0.3": 97.4359,
              "R@5,IoU=0.5": 87.6068,
              "R@5,IoU=0.7": 61.1111
            },
            "CPL_MoE": {
              "R@1,IoU=0.3": 59.4017,
              "R@1,IoU=0.5": 47.0085,
              "R@1,IoU=0.7": 24.7863,
              "mIoU": 41.9109,
              "count": 234,
              "R@5,mIoU": 69.4492,
              "R@5,IoU=0.3": 97.0085,
              "R@5,IoU=0.5": 88.0342,
              "R@5,IoU=0.7": 59.4017
            },
            "CPL_DMVS": {
              "R@1,IoU=0.3": 35.4701,
              "R@1,IoU=0.5": 26.0684,
              "R@1,IoU=0.7": 14.5299,
              "mIoU": 26.1474,
              "count": 234,
              "R@5,mIoU": 64.0027,
              "R@5,IoU=0.3": 93.1624,
              "R@5,IoU=0.5": 78.6325,
              "R@5,IoU=0.7": 46.5812
            }
          }
        },
        {
          "slice": "movement,perception",
          "count": 76,
          "ratio": 0.024066,
          "models_percent": {
            "CPL": {
              "R@1,IoU=0.3": 65.7895,
              "R@1,IoU=0.5": 47.3684,
              "R@1,IoU=0.7": 28.9474,
              "mIoU": 45.7024,
              "count": 76,
              "R@5,mIoU": 70.6522,
              "R@5,IoU=0.3": 94.7368,
              "R@5,IoU=0.5": 84.2105,
              "R@5,IoU=0.7": 65.7895
            },
            "CPL_MoE": {
              "R@1,IoU=0.3": 56.5789,
              "R@1,IoU=0.5": 39.4737,
              "R@1,IoU=0.7": 31.5789,
              "mIoU": 38.9807,
              "count": 76,
              "R@5,mIoU": 71.2491,
              "R@5,IoU=0.3": 97.3684,
              "R@5,IoU=0.5": 88.1579,
              "R@5,IoU=0.7": 67.1053
            },
            "CPL_DMVS": {
              "R@1,IoU=0.3": 42.1053,
              "R@1,IoU=0.5": 31.5789,
              "R@1,IoU=0.7": 13.1579,
              "mIoU": 27.1393,
              "count": 76,
              "R@5,mIoU": 65.9202,
              "R@5,IoU=0.3": 92.1053,
              "R@5,IoU=0.5": 78.9474,
              "R@5,IoU=0.7": 57.8947
            }
          }
        },
        {
          "slice": "perception,state_change",
          "count": 68,
          "ratio": 0.021533,
          "models_percent": {
            "CPL": {
              "R@1,IoU=0.3": 51.4706,
              "R@1,IoU=0.5": 36.7647,
              "R@1,IoU=0.7": 16.1765,
              "mIoU": 33.581,
              "count": 68,
              "R@5,mIoU": 66.1709,
              "R@5,IoU=0.3": 95.5882,
              "R@5,IoU=0.5": 83.8235,
              "R@5,IoU=0.7": 45.5882
            },
            "CPL_MoE": {
              "R@1,IoU=0.3": 55.8824,
              "R@1,IoU=0.5": 33.8235,
              "R@1,IoU=0.7": 11.7647,
              "mIoU": 33.6532,
              "count": 68,
              "R@5,mIoU": 70.1819,
              "R@5,IoU=0.3": 100.0,
              "R@5,IoU=0.5": 91.1765,
              "R@5,IoU=0.7": 52.9412
            },
            "CPL_DMVS": {
              "R@1,IoU=0.3": 35.2941,
              "R@1,IoU=0.5": 20.5882,
              "R@1,IoU=0.7": 5.8824,
              "mIoU": 21.1522,
              "count": 68,
              "R@5,mIoU": 63.2596,
              "R@5,IoU=0.3": 95.5882,
              "R@5,IoU=0.5": 77.9412,
              "R@5,IoU=0.7": 35.2941
            }
          }
        },
        {
          "slice": "interaction,movement",
          "count": 63,
          "ratio": 0.019949,
          "models_percent": {
            "CPL": {
              "R@1,IoU=0.3": 73.0159,
              "R@1,IoU=0.5": 58.7302,
              "R@1,IoU=0.7": 26.9841,
              "mIoU": 50.4507,
              "count": 63,
              "R@5,mIoU": 72.2383,
              "R@5,IoU=0.3": 98.4127,
              "R@5,IoU=0.5": 87.3016,
              "R@5,IoU=0.7": 68.254
            },
            "CPL_MoE": {
              "R@1,IoU=0.3": 77.7778,
              "R@1,IoU=0.5": 61.9048,
              "R@1,IoU=0.7": 39.6825,
              "mIoU": 54.3391,
              "count": 63,
              "R@5,mIoU": 72.116,
              "R@5,IoU=0.3": 98.4127,
              "R@5,IoU=0.5": 87.3016,
              "R@5,IoU=0.7": 65.0794
            },
            "CPL_DMVS": {
              "R@1,IoU=0.3": 47.619,
              "R@1,IoU=0.5": 30.1587,
              "R@1,IoU=0.7": 14.2857,
              "mIoU": 32.2767,
              "count": 63,
              "R@5,mIoU": 64.6099,
              "R@5,IoU=0.3": 93.6508,
              "R@5,IoU=0.5": 76.1905,
              "R@5,IoU=0.7": 49.2063
            }
          }
        },
        {
          "slice": "interaction,perception",
          "count": 56,
          "ratio": 0.017733,
          "models_percent": {
            "CPL": {
              "R@1,IoU=0.3": 57.1429,
              "R@1,IoU=0.5": 42.8571,
              "R@1,IoU=0.7": 21.4286,
              "mIoU": 37.9274,
              "count": 56,
              "R@5,mIoU": 69.8789,
              "R@5,IoU=0.3": 100.0,
              "R@5,IoU=0.5": 89.2857,
              "R@5,IoU=0.7": 57.1429
            },
            "CPL_MoE": {
              "R@1,IoU=0.3": 58.9286,
              "R@1,IoU=0.5": 46.4286,
              "R@1,IoU=0.7": 26.7857,
              "mIoU": 41.0824,
              "count": 56,
              "R@5,mIoU": 68.7736,
              "R@5,IoU=0.3": 98.2143,
              "R@5,IoU=0.5": 87.5,
              "R@5,IoU=0.7": 57.1429
            },
            "CPL_DMVS": {
              "R@1,IoU=0.3": 46.4286,
              "R@1,IoU=0.5": 21.4286,
              "R@1,IoU=0.7": 8.9286,
              "mIoU": 27.8456,
              "count": 56,
              "R@5,mIoU": 64.9629,
              "R@5,IoU=0.3": 98.2143,
              "R@5,IoU=0.5": 76.7857,
              "R@5,IoU=0.7": 46.4286
            }
          }
        },
        {
          "slice": "interaction,state_change",
          "count": 49,
          "ratio": 0.015516,
          "models_percent": {
            "CPL": {
              "R@1,IoU=0.3": 65.3061,
              "R@1,IoU=0.5": 32.6531,
              "R@1,IoU=0.7": 16.3265,
              "mIoU": 38.6422,
              "count": 49,
              "R@5,mIoU": 66.3097,
              "R@5,IoU=0.3": 97.9592,
              "R@5,IoU=0.5": 83.6735,
              "R@5,IoU=0.7": 44.898
            },
            "CPL_MoE": {
              "R@1,IoU=0.3": 75.5102,
              "R@1,IoU=0.5": 42.8571,
              "R@1,IoU=0.7": 12.2449,
              "mIoU": 42.1932,
              "count": 49,
              "R@5,mIoU": 66.3061,
              "R@5,IoU=0.3": 95.9184,
              "R@5,IoU=0.5": 81.6327,
              "R@5,IoU=0.7": 46.9388
            },
            "CPL_DMVS": {
              "R@1,IoU=0.3": 44.898,
              "R@1,IoU=0.5": 30.6122,
              "R@1,IoU=0.7": 8.1633,
              "mIoU": 28.4975,
              "count": 49,
              "R@5,mIoU": 59.1061,
              "R@5,IoU=0.3": 87.7551,
              "R@5,IoU=0.5": 69.3878,
              "R@5,IoU=0.7": 34.6939
            }
          }
        },
        {
          "slice": "movement,state_change",
          "count": 33,
          "ratio": 0.01045,
          "models_percent": {
            "CPL": {
              "R@1,IoU=0.3": 78.7879,
              "R@1,IoU=0.5": 45.4545,
              "R@1,IoU=0.7": 30.303,
              "mIoU": 46.5287,
              "count": 33,
              "R@5,mIoU": 68.193,
              "R@5,IoU=0.3": 100.0,
              "R@5,IoU=0.5": 84.8485,
              "R@5,IoU=0.7": 60.6061
            },
            "CPL_MoE": {
              "R@1,IoU=0.3": 69.697,
              "R@1,IoU=0.5": 48.4848,
              "R@1,IoU=0.7": 21.2121,
              "mIoU": 43.6118,
              "count": 33,
              "R@5,mIoU": 66.1279,
              "R@5,IoU=0.3": 100.0,
              "R@5,IoU=0.5": 84.8485,
              "R@5,IoU=0.7": 51.5152
            },
            "CPL_DMVS": {
              "R@1,IoU=0.3": 45.4545,
              "R@1,IoU=0.5": 21.2121,
              "R@1,IoU=0.7": 6.0606,
              "mIoU": 25.3479,
              "count": 33,
              "R@5,mIoU": 64.2914,
              "R@5,IoU=0.3": 93.9394,
              "R@5,IoU=0.5": 81.8182,
              "R@5,IoU=0.7": 54.5455
            }
          }
        },
        {
          "slice": "interaction,perception,state_change",
          "count": 2,
          "ratio": 0.000633,
          "models_percent": {
            "CPL": {
              "R@1,IoU=0.3": 100.0,
              "R@1,IoU=0.5": 100.0,
              "R@1,IoU=0.7": 100.0,
              "mIoU": 79.9396,
              "count": 2,
              "R@5,mIoU": 79.9396,
              "R@5,IoU=0.3": 100.0,
              "R@5,IoU=0.5": 100.0,
              "R@5,IoU=0.7": 100.0
            },
            "CPL_MoE": {
              "R@1,IoU=0.3": 100.0,
              "R@1,IoU=0.5": 100.0,
              "R@1,IoU=0.7": 50.0,
              "mIoU": 65.3464,
              "count": 2,
              "R@5,mIoU": 76.9499,
              "R@5,IoU=0.3": 100.0,
              "R@5,IoU=0.5": 100.0,
              "R@5,IoU=0.7": 100.0
            },
            "CPL_DMVS": {
              "R@1,IoU=0.3": 50.0,
              "R@1,IoU=0.5": 50.0,
              "R@1,IoU=0.7": 0.0,
              "mIoU": 31.1297,
              "count": 2,
              "R@5,mIoU": 81.6271,
              "R@5,IoU=0.3": 100.0,
              "R@5,IoU=0.5": 100.0,
              "R@5,IoU=0.7": 100.0
            }
          }
        },
        {
          "slice": "movement,perception,state_change",
          "count": 2,
          "ratio": 0.000633,
          "models_percent": {
            "CPL": {
              "R@1,IoU=0.3": 100.0,
              "R@1,IoU=0.5": 50.0,
              "R@1,IoU=0.7": 0.0,
              "mIoU": 56.8584,
              "count": 2,
              "R@5,mIoU": 74.9862,
              "R@5,IoU=0.3": 100.0,
              "R@5,IoU=0.5": 100.0,
              "R@5,IoU=0.7": 50.0
            },
            "CPL_MoE": {
              "R@1,IoU=0.3": 100.0,
              "R@1,IoU=0.5": 50.0,
              "R@1,IoU=0.7": 50.0,
              "mIoU": 58.6004,
              "count": 2,
              "R@5,mIoU": 65.4806,
              "R@5,IoU=0.3": 100.0,
              "R@5,IoU=0.5": 100.0,
              "R@5,IoU=0.7": 50.0
            },
            "CPL_DMVS": {
              "R@1,IoU=0.3": 50.0,
              "R@1,IoU=0.5": 0.0,
              "R@1,IoU=0.7": 0.0,
              "mIoU": 24.1129,
              "count": 2,
              "R@5,mIoU": 73.8793,
              "R@5,IoU=0.3": 100.0,
              "R@5,IoU=0.5": 100.0,
              "R@5,IoU=0.7": 50.0
            }
          }
        },
        {
          "slice": "interaction,movement,perception",
          "count": 1,
          "ratio": 0.000317,
          "models_percent": {
            "CPL": {
              "R@1,IoU=0.3": 100.0,
              "R@1,IoU=0.5": 0.0,
              "R@1,IoU=0.7": 0.0,
              "mIoU": 37.9699,
              "count": 1,
              "R@5,mIoU": 52.9452,
              "R@5,IoU=0.3": 100.0,
              "R@5,IoU=0.5": 100.0,
              "R@5,IoU=0.7": 0.0
            },
            "CPL_MoE": {
              "R@1,IoU=0.3": 0.0,
              "R@1,IoU=0.5": 0.0,
              "R@1,IoU=0.7": 0.0,
              "mIoU": 0.0,
              "count": 1,
              "R@5,mIoU": 54.6718,
              "R@5,IoU=0.3": 100.0,
              "R@5,IoU=0.5": 100.0,
              "R@5,IoU=0.7": 0.0
            },
            "CPL_DMVS": {
              "R@1,IoU=0.3": 0.0,
              "R@1,IoU=0.5": 0.0,
              "R@1,IoU=0.7": 0.0,
              "mIoU": 0.0,
              "count": 1,
              "R@5,mIoU": 34.8773,
              "R@5,IoU=0.3": 100.0,
              "R@5,IoU=0.5": 0.0,
              "R@5,IoU=0.7": 0.0
            }
          }
        },
        {
          "slice": "interaction,movement,state_change",
          "count": 1,
          "ratio": 0.000317,
          "models_percent": {
            "CPL": {
              "R@1,IoU=0.3": 0.0,
              "R@1,IoU=0.5": 0.0,
              "R@1,IoU=0.7": 0.0,
              "mIoU": 9.7833,
              "count": 1,
              "R@5,mIoU": 85.9919,
              "R@5,IoU=0.3": 100.0,
              "R@5,IoU=0.5": 100.0,
              "R@5,IoU=0.7": 100.0
            },
            "CPL_MoE": {
              "R@1,IoU=0.3": 100.0,
              "R@1,IoU=0.5": 0.0,
              "R@1,IoU=0.7": 0.0,
              "mIoU": 45.2021,
              "count": 1,
              "R@5,mIoU": 88.896,
              "R@5,IoU=0.3": 100.0,
              "R@5,IoU=0.5": 100.0,
              "R@5,IoU=0.7": 100.0
            },
            "CPL_DMVS": {
              "R@1,IoU=0.3": 0.0,
              "R@1,IoU=0.5": 0.0,
              "R@1,IoU=0.7": 0.0,
              "mIoU": 0.0,
              "count": 1,
              "R@5,mIoU": 84.9859,
              "R@5,IoU=0.3": 100.0,
              "R@5,IoU=0.5": 100.0,
              "R@5,IoU=0.7": 100.0
            }
          }
        }
      ]
    },
    "has_person_subject": {
      "dimension": "has_person_subject",
      "num_slices": 2,
      "slices": [
        {
          "slice": "True",
          "count": 3155,
          "ratio": 0.99905,
          "models_percent": {
            "CPL": {
              "R@1,IoU=0.3": 66.0856,
              "R@1,IoU=0.5": 47.7971,
              "R@1,IoU=0.7": 22.7892,
              "mIoU": 43.2033,
              "count": 3155,
              "R@5,mIoU": 66.6429,
              "R@5,IoU=0.3": 96.9255,
              "R@5,IoU=0.5": 82.7258,
              "R@5,IoU=0.7": 49.6989
            },
            "CPL_MoE": {
              "R@1,IoU=0.3": 64.3423,
              "R@1,IoU=0.5": 46.2124,
              "R@1,IoU=0.7": 21.3946,
              "mIoU": 41.6802,
              "count": 3155,
              "R@5,mIoU": 66.2896,
              "R@5,IoU=0.3": 97.401,
              "R@5,IoU=0.5": 83.0428,
              "R@5,IoU=0.7": 48.4628
            },
            "CPL_DMVS": {
              "R@1,IoU=0.3": 37.7813,
              "R@1,IoU=0.5": 24.5008,
              "R@1,IoU=0.7": 10.0475,
              "mIoU": 24.8609,
              "count": 3155,
              "R@5,mIoU": 60.7438,
              "R@5,IoU=0.3": 90.9033,
              "R@5,IoU=0.5": 72.8685,
              "R@5,IoU=0.7": 40.0317
            }
          }
        },
        {
          "slice": "False",
          "count": 3,
          "ratio": 0.00095,
          "models_percent": {
            "CPL": {
              "R@1,IoU=0.3": 33.3333,
              "R@1,IoU=0.5": 33.3333,
              "R@1,IoU=0.7": 0.0,
              "mIoU": 26.5775,
              "count": 3,
              "R@5,mIoU": 64.1803,
              "R@5,IoU=0.3": 100.0,
              "R@5,IoU=0.5": 100.0,
              "R@5,IoU=0.7": 33.3333
            },
            "CPL_MoE": {
              "R@1,IoU=0.3": 66.6667,
              "R@1,IoU=0.5": 33.3333,
              "R@1,IoU=0.7": 0.0,
              "mIoU": 33.0816,
              "count": 3,
              "R@5,mIoU": 63.2636,
              "R@5,IoU=0.3": 100.0,
              "R@5,IoU=0.5": 100.0,
              "R@5,IoU=0.7": 33.3333
            },
            "CPL_DMVS": {
              "R@1,IoU=0.3": 33.3333,
              "R@1,IoU=0.5": 0.0,
              "R@1,IoU=0.7": 0.0,
              "mIoU": 25.6999,
              "count": 3,
              "R@5,mIoU": 62.6555,
              "R@5,IoU=0.3": 100.0,
              "R@5,IoU=0.5": 100.0,
              "R@5,IoU=0.7": 33.3333
            }
          }
        }
      ]
    },
    "has_temporal_cue": {
      "dimension": "has_temporal_cue",
      "num_slices": 2,
      "slices": [
        {
          "slice": "False",
          "count": 3051,
          "ratio": 0.966118,
          "models_percent": {
            "CPL": {
              "R@1,IoU=0.3": 66.0111,
              "R@1,IoU=0.5": 47.8859,
              "R@1,IoU=0.7": 22.9761,
              "mIoU": 43.2178,
              "count": 3051,
              "R@5,mIoU": 66.5881,
              "R@5,IoU=0.3": 96.919,
              "R@5,IoU=0.5": 82.727,
              "R@5,IoU=0.7": 49.5903
            },
            "CPL_MoE": {
              "R@1,IoU=0.3": 64.2085,
              "R@1,IoU=0.5": 46.2144,
              "R@1,IoU=0.7": 21.2717,
              "mIoU": 41.6037,
              "count": 3051,
              "R@5,mIoU": 66.1944,
              "R@5,IoU=0.3": 97.4435,
              "R@5,IoU=0.5": 83.022,
              "R@5,IoU=0.7": 48.017
            },
            "CPL_DMVS": {
              "R@1,IoU=0.3": 37.4304,
              "R@1,IoU=0.5": 24.0905,
              "R@1,IoU=0.7": 9.8328,
              "mIoU": 24.5945,
              "count": 3051,
              "R@5,mIoU": 60.6121,
              "R@5,IoU=0.3": 90.8882,
              "R@5,IoU=0.5": 72.7303,
              "R@5,IoU=0.7": 39.5936
            }
          }
        },
        {
          "slice": "True",
          "count": 107,
          "ratio": 0.033882,
          "models_percent": {
            "CPL": {
              "R@1,IoU=0.3": 67.2897,
              "R@1,IoU=0.5": 44.8598,
              "R@1,IoU=0.7": 16.8224,
              "mIoU": 42.3239,
              "count": 107,
              "R@5,mIoU": 68.1387,
              "R@5,IoU=0.3": 97.1963,
              "R@5,IoU=0.5": 83.1776,
              "R@5,IoU=0.7": 52.3364
            },
            "CPL_MoE": {
              "R@1,IoU=0.3": 68.2243,
              "R@1,IoU=0.5": 45.7944,
              "R@1,IoU=0.7": 24.2991,
              "mIoU": 43.6195,
              "count": 107,
              "R@5,mIoU": 68.9174,
              "R@5,IoU=0.3": 96.2617,
              "R@5,IoU=0.5": 84.1121,
              "R@5,IoU=0.7": 60.7477
            },
            "CPL_DMVS": {
              "R@1,IoU=0.3": 47.6636,
              "R@1,IoU=0.5": 35.514,
              "R@1,IoU=0.7": 15.8879,
              "mIoU": 32.4824,
              "count": 107,
              "R@5,mIoU": 64.5515,
              "R@5,IoU=0.3": 91.5888,
              "R@5,IoU=0.5": 77.5701,
              "R@5,IoU=0.7": 52.3364
            }
          }
        }
      ]
    },
    "gt_coverage_bucket": {
      "dimension": "gt_coverage_bucket",
      "num_slices": 4,
      "slices": [
        {
          "slice": "small(10-30%)",
          "count": 2052,
          "ratio": 0.649778,
          "models_percent": {
            "CPL": {
              "R@1,IoU=0.3": 61.8908,
              "R@1,IoU=0.5": 40.8382,
              "R@1,IoU=0.7": 14.4737,
              "mIoU": 38.0477,
              "count": 2052,
              "R@5,mIoU": 60.8918,
              "R@5,IoU=0.3": 96.4425,
              "R@5,IoU=0.5": 76.0721,
              "R@5,IoU=0.7": 31.4815
            },
            "CPL_MoE": {
              "R@1,IoU=0.3": 61.1598,
              "R@1,IoU=0.5": 40.6433,
              "R@1,IoU=0.7": 13.5965,
              "mIoU": 37.0866,
              "count": 2052,
              "R@5,mIoU": 60.1102,
              "R@5,IoU=0.3": 97.1248,
              "R@5,IoU=0.5": 76.2183,
              "R@5,IoU=0.7": 29.0448
            },
            "CPL_DMVS": {
              "R@1,IoU=0.3": 32.6511,
              "R@1,IoU=0.5": 19.4932,
              "R@1,IoU=0.7": 6.1891,
              "mIoU": 20.7644,
              "count": 2052,
              "R@5,mIoU": 55.0316,
              "R@5,IoU=0.3": 87.3782,
              "R@5,IoU=0.5": 64.5224,
              "R@5,IoU=0.7": 26.0721
            }
          }
        },
        {
          "slice": "medium(30-50%)",
          "count": 1068,
          "ratio": 0.338189,
          "models_percent": {
            "CPL": {
              "R@1,IoU=0.3": 75.3745,
              "R@1,IoU=0.5": 62.1723,
              "R@1,IoU=0.7": 39.5131,
              "mIoU": 53.819,
              "count": 1068,
              "R@5,mIoU": 78.7487,
              "R@5,IoU=0.3": 99.6255,
              "R@5,IoU=0.5": 97.191,
              "R@5,IoU=0.7": 86.3296
            },
            "CPL_MoE": {
              "R@1,IoU=0.3": 71.8165,
              "R@1,IoU=0.5": 57.9588,
              "R@1,IoU=0.7": 37.0787,
              "mIoU": 51.211,
              "count": 1068,
              "R@5,mIoU": 79.205,
              "R@5,IoU=0.3": 99.8127,
              "R@5,IoU=0.5": 97.8464,
              "R@5,IoU=0.7": 87.3596
            },
            "CPL_DMVS": {
              "R@1,IoU=0.3": 47.7528,
              "R@1,IoU=0.5": 34.2697,
              "R@1,IoU=0.7": 17.7903,
              "mIoU": 32.9021,
              "count": 1068,
              "R@5,mIoU": 72.6695,
              "R@5,IoU=0.3": 99.0637,
              "R@5,IoU=0.5": 90.2622,
              "R@5,IoU=0.7": 68.1648
            }
          }
        },
        {
          "slice": "tiny(<=10%)",
          "count": 24,
          "ratio": 0.0076,
          "models_percent": {
            "CPL": {
              "R@1,IoU=0.3": 4.1667,
              "R@1,IoU=0.5": 0.0,
              "R@1,IoU=0.7": 0.0,
              "mIoU": 8.8891,
              "count": 24,
              "R@5,mIoU": 18.6553,
              "R@5,IoU=0.3": 16.6667,
              "R@5,IoU=0.5": 0.0,
              "R@5,IoU=0.7": 0.0
            },
            "CPL_MoE": {
              "R@1,IoU=0.3": 4.1667,
              "R@1,IoU=0.5": 0.0,
              "R@1,IoU=0.7": 0.0,
              "mIoU": 9.5842,
              "count": 24,
              "R@5,mIoU": 18.5735,
              "R@5,IoU=0.3": 12.5,
              "R@5,IoU=0.5": 0.0,
              "R@5,IoU=0.7": 0.0
            },
            "CPL_DMVS": {
              "R@1,IoU=0.3": 8.3333,
              "R@1,IoU=0.5": 0.0,
              "R@1,IoU=0.7": 0.0,
              "mIoU": 3.9012,
              "count": 24,
              "R@5,mIoU": 14.0821,
              "R@5,IoU=0.3": 25.0,
              "R@5,IoU=0.5": 0.0,
              "R@5,IoU=0.7": 0.0
            }
          }
        },
        {
          "slice": "large(50-70%)",
          "count": 14,
          "ratio": 0.004433,
          "models_percent": {
            "CPL": {
              "R@1,IoU=0.3": 71.4286,
              "R@1,IoU=0.5": 50.0,
              "R@1,IoU=0.7": 0.0,
              "mIoU": 44.2999,
              "count": 14,
              "R@5,mIoU": 67.838,
              "R@5,IoU=0.3": 100.0,
              "R@5,IoU=0.5": 100.0,
              "R@5,IoU=0.7": 7.1429
            },
            "CPL_MoE": {
              "R@1,IoU=0.3": 64.2857,
              "R@1,IoU=0.5": 42.8571,
              "R@1,IoU=0.7": 0.0,
              "mIoU": 41.0842,
              "count": 14,
              "R@5,mIoU": 67.8977,
              "R@5,IoU=0.3": 100.0,
              "R@5,IoU=0.5": 100.0,
              "R@5,IoU=0.7": 7.1429
            },
            "CPL_DMVS": {
              "R@1,IoU=0.3": 78.5714,
              "R@1,IoU=0.5": 50.0,
              "R@1,IoU=0.7": 0.0,
              "mIoU": 47.9776,
              "count": 14,
              "R@5,mIoU": 68.615,
              "R@5,IoU=0.3": 100.0,
              "R@5,IoU=0.5": 100.0,
              "R@5,IoU=0.7": 7.1429
            }
          }
        }
      ]
    },
    "gt_position_bucket": {
      "dimension": "gt_position_bucket",
      "num_slices": 3,
      "slices": [
        {
          "slice": "beginning",
          "count": 1595,
          "ratio": 0.505066,
          "models_percent": {
            "CPL": {
              "R@1,IoU=0.3": 69.279,
              "R@1,IoU=0.5": 51.0972,
              "R@1,IoU=0.7": 26.0815,
              "mIoU": 45.5947,
              "count": 1595,
              "R@5,mIoU": 65.5684,
              "R@5,IoU=0.3": 94.6082,
              "R@5,IoU=0.5": 78.2445,
              "R@5,IoU=0.7": 49.7806
            },
            "CPL_MoE": {
              "R@1,IoU=0.3": 61.1912,
              "R@1,IoU=0.5": 42.6959,
              "R@1,IoU=0.7": 22.7586,
              "mIoU": 39.8174,
              "count": 1595,
              "R@5,mIoU": 65.3157,
              "R@5,IoU=0.3": 95.7367,
              "R@5,IoU=0.5": 78.558,
              "R@5,IoU=0.7": 48.0251
            },
            "CPL_DMVS": {
              "R@1,IoU=0.3": 25.8934,
              "R@1,IoU=0.5": 16.4263,
              "R@1,IoU=0.7": 7.837,
              "mIoU": 17.5428,
              "count": 1595,
              "R@5,mIoU": 55.2477,
              "R@5,IoU=0.3": 83.2602,
              "R@5,IoU=0.5": 62.0063,
              "R@5,IoU=0.7": 33.4169
            }
          }
        },
        {
          "slice": "middle",
          "count": 998,
          "ratio": 0.316023,
          "models_percent": {
            "CPL": {
              "R@1,IoU=0.3": 61.6232,
              "R@1,IoU=0.5": 41.8838,
              "R@1,IoU=0.7": 17.9359,
              "mIoU": 40.5435,
              "count": 998,
              "R@5,mIoU": 68.4488,
              "R@5,IoU=0.3": 100.0,
              "R@5,IoU=0.5": 89.2786,
              "R@5,IoU=0.7": 51.1022
            },
            "CPL_MoE": {
              "R@1,IoU=0.3": 65.4309,
              "R@1,IoU=0.5": 47.2946,
              "R@1,IoU=0.7": 17.8357,
              "mIoU": 42.2328,
              "count": 998,
              "R@5,mIoU": 67.6882,
              "R@5,IoU=0.3": 99.7996,
              "R@5,IoU=0.5": 89.0782,
              "R@5,IoU=0.7": 50.7014
            },
            "CPL_DMVS": {
              "R@1,IoU=0.3": 47.7956,
              "R@1,IoU=0.5": 30.3607,
              "R@1,IoU=0.7": 10.1202,
              "mIoU": 31.0707,
              "count": 998,
              "R@5,mIoU": 66.7338,
              "R@5,IoU=0.3": 99.499,
              "R@5,IoU=0.5": 85.4709,
              "R@5,IoU=0.7": 47.1944
            }
          }
        },
        {
          "slice": "end",
          "count": 565,
          "ratio": 0.178911,
          "models_percent": {
            "CPL": {
              "R@1,IoU=0.3": 64.7788,
              "R@1,IoU=0.5": 48.8496,
              "R@1,IoU=0.7": 21.9469,
              "mIoU": 41.0624,
              "count": 565,
              "R@5,mIoU": 66.4734,
              "R@5,IoU=0.3": 98.0531,
              "R@5,IoU=0.5": 83.8938,
              "R@5,IoU=0.7": 46.9027
            },
            "CPL_MoE": {
              "R@1,IoU=0.3": 71.3274,
              "R@1,IoU=0.5": 54.1593,
              "R@1,IoU=0.7": 23.7168,
              "mIoU": 45.917,
              "count": 565,
              "R@5,mIoU": 66.5523,
              "R@5,IoU=0.3": 97.8761,
              "R@5,IoU=0.5": 85.1327,
              "R@5,IoU=0.7": 45.6637
            },
            "CPL_DMVS": {
              "R@1,IoU=0.3": 53.6283,
              "R@1,IoU=0.5": 36.8142,
              "R@1,IoU=0.7": 16.1062,
              "mIoU": 34.5558,
              "count": 565,
              "R@5,mIoU": 65.6886,
              "R@5,IoU=0.3": 97.3451,
              "R@5,IoU=0.5": 81.4159,
              "R@5,IoU=0.7": 46.0177
            }
          }
        }
      ]
    },
    "video_length_bucket": {
      "dimension": "video_length_bucket",
      "num_slices": 3,
      "slices": [
        {
          "slice": "short(20-40s)",
          "count": 2608,
          "ratio": 0.825839,
          "models_percent": {
            "CPL": {
              "R@1,IoU=0.3": 66.2577,
              "R@1,IoU=0.5": 46.8942,
              "R@1,IoU=0.7": 21.7025,
              "mIoU": 42.8221,
              "count": 2608,
              "R@5,mIoU": 66.0255,
              "R@5,IoU=0.3": 97.0092,
              "R@5,IoU=0.5": 82.8221,
              "R@5,IoU=0.7": 46.7408
            },
            "CPL_MoE": {
              "R@1,IoU=0.3": 64.8006,
              "R@1,IoU=0.5": 46.4724,
              "R@1,IoU=0.7": 20.092,
              "mIoU": 41.6007,
              "count": 2608,
              "R@5,mIoU": 65.4818,
              "R@5,IoU=0.3": 97.5077,
              "R@5,IoU=0.5": 82.8604,
              "R@5,IoU=0.7": 44.7469
            },
            "CPL_DMVS": {
              "R@1,IoU=0.3": 36.9248,
              "R@1,IoU=0.5": 23.6196,
              "R@1,IoU=0.7": 9.0874,
              "mIoU": 24.1181,
              "count": 2608,
              "R@5,mIoU": 59.7067,
              "R@5,IoU=0.3": 90.2991,
              "R@5,IoU=0.5": 72.1626,
              "R@5,IoU=0.7": 37.1933
            }
          }
        },
        {
          "slice": "very_short(<=20s)",
          "count": 351,
          "ratio": 0.111146,
          "models_percent": {
            "CPL": {
              "R@1,IoU=0.3": 71.51,
              "R@1,IoU=0.5": 60.9687,
              "R@1,IoU=0.7": 35.8974,
              "mIoU": 50.8227,
              "count": 351,
              "R@5,mIoU": 76.1912,
              "R@5,IoU=0.3": 98.5755,
              "R@5,IoU=0.5": 93.4473,
              "R@5,IoU=0.7": 79.7721
            },
            "CPL_MoE": {
              "R@1,IoU=0.3": 63.5328,
              "R@1,IoU=0.5": 49.8575,
              "R@1,IoU=0.7": 33.6182,
              "mIoU": 45.0701,
              "count": 351,
              "R@5,mIoU": 76.6917,
              "R@5,IoU=0.3": 98.8604,
              "R@5,IoU=0.5": 96.0114,
              "R@5,IoU=0.7": 82.906
            },
            "CPL_DMVS": {
              "R@1,IoU=0.3": 45.2991,
              "R@1,IoU=0.5": 35.0427,
              "R@1,IoU=0.7": 18.5185,
              "mIoU": 32.1478,
              "count": 351,
              "R@5,mIoU": 71.8251,
              "R@5,IoU=0.3": 95.1567,
              "R@5,IoU=0.5": 88.604,
              "R@5,IoU=0.7": 66.6667
            }
          }
        },
        {
          "slice": "medium(40-80s)",
          "count": 199,
          "ratio": 0.063015,
          "models_percent": {
            "CPL": {
              "R@1,IoU=0.3": 53.7688,
              "R@1,IoU=0.5": 36.1809,
              "R@1,IoU=0.7": 13.5678,
              "mIoU": 34.5099,
              "count": 199,
              "R@5,mIoU": 57.8565,
              "R@5,IoU=0.3": 92.9648,
              "R@5,IoU=0.5": 62.8141,
              "R@5,IoU=0.7": 35.1759
            },
            "CPL_MoE": {
              "R@1,IoU=0.3": 59.799,
              "R@1,IoU=0.5": 36.1809,
              "R@1,IoU=0.7": 16.5829,
              "mIoU": 36.6129,
              "count": 199,
              "R@5,mIoU": 58.4822,
              "R@5,IoU=0.3": 93.4673,
              "R@5,IoU=0.5": 62.8141,
              "R@5,IoU=0.7": 36.1809
            },
            "CPL_DMVS": {
              "R@1,IoU=0.3": 35.6784,
              "R@1,IoU=0.5": 17.0854,
              "R@1,IoU=0.7": 7.5377,
              "mIoU": 21.7557,
              "count": 199,
              "R@5,mIoU": 54.8178,
              "R@5,IoU=0.3": 91.4573,
              "R@5,IoU=0.5": 54.7739,
              "R@5,IoU=0.7": 30.1508
            }
          }
        }
      ]
    },
    "gt_length_bucket": {
      "dimension": "gt_length_bucket",
      "num_slices": 4,
      "slices": [
        {
          "slice": "short(3-8s)",
          "count": 1959,
          "ratio": 0.620329,
          "models_percent": {
            "CPL": {
              "R@1,IoU=0.3": 62.3277,
              "R@1,IoU=0.5": 40.633,
              "R@1,IoU=0.7": 13.6294,
              "mIoU": 38.2184,
              "count": 1959,
              "R@5,mIoU": 60.721,
              "R@5,IoU=0.3": 96.1715,
              "R@5,IoU=0.5": 74.9362,
              "R@5,IoU=0.7": 31.6488
            },
            "CPL_MoE": {
              "R@1,IoU=0.3": 61.1026,
              "R@1,IoU=0.5": 40.1225,
              "R@1,IoU=0.7": 12.3532,
              "mIoU": 37.0695,
              "count": 1959,
              "R@5,mIoU": 60.0833,
              "R@5,IoU=0.3": 96.682,
              "R@5,IoU=0.5": 75.2425,
              "R@5,IoU=0.7": 28.6371
            },
            "CPL_DMVS": {
              "R@1,IoU=0.3": 34.099,
              "R@1,IoU=0.5": 21.1332,
              "R@1,IoU=0.7": 6.8402,
              "mIoU": 21.7783,
              "count": 1959,
              "R@5,mIoU": 55.0887,
              "R@5,IoU=0.3": 87.3915,
              "R@5,IoU=0.5": 64.5738,
              "R@5,IoU=0.7": 26.1358
            }
          }
        },
        {
          "slice": "medium(8-20s)",
          "count": 1182,
          "ratio": 0.374288,
          "models_percent": {
            "CPL": {
              "R@1,IoU=0.3": 73.0118,
              "R@1,IoU=0.5": 60.1523,
              "R@1,IoU=0.7": 38.1557,
              "mIoU": 51.8301,
              "count": 1182,
              "R@5,mIoU": 76.9847,
              "R@5,IoU=0.3": 99.2386,
              "R@5,IoU=0.5": 96.5313,
              "R@5,IoU=0.7": 80.0338
            },
            "CPL_MoE": {
              "R@1,IoU=0.3": 70.3046,
              "R@1,IoU=0.5": 56.8528,
              "R@1,IoU=0.7": 36.5482,
              "mIoU": 49.6909,
              "count": 1182,
              "R@5,mIoU": 77.0562,
              "R@5,IoU=0.3": 99.4924,
              "R@5,IoU=0.5": 96.8697,
              "R@5,IoU=0.7": 81.6413
            },
            "CPL_DMVS": {
              "R@1,IoU=0.3": 44.247,
              "R@1,IoU=0.5": 30.3723,
              "R@1,IoU=0.7": 15.4822,
              "mIoU": 30.2436,
              "count": 1182,
              "R@5,mIoU": 70.6404,
              "R@5,IoU=0.3": 97.4619,
              "R@5,IoU=0.5": 87.4788,
              "R@5,IoU=0.7": 63.3672
            }
          }
        },
        {
          "slice": "very_short(<=3s)",
          "count": 14,
          "ratio": 0.004433,
          "models_percent": {
            "CPL": {
              "R@1,IoU=0.3": 7.1429,
              "R@1,IoU=0.5": 7.1429,
              "R@1,IoU=0.7": 7.1429,
              "mIoU": 10.247,
              "count": 14,
              "R@5,mIoU": 20.0122,
              "R@5,IoU=0.3": 7.1429,
              "R@5,IoU=0.5": 7.1429,
              "R@5,IoU=0.7": 7.1429
            },
            "CPL_MoE": {
              "R@1,IoU=0.3": 7.1429,
              "R@1,IoU=0.5": 0.0,
              "R@1,IoU=0.7": 0.0,
              "mIoU": 5.7565,
              "count": 14,
              "R@5,mIoU": 23.3727,
              "R@5,IoU=0.3": 21.4286,
              "R@5,IoU=0.5": 7.1429,
              "R@5,IoU=0.7": 7.1429
            },
            "CPL_DMVS": {
              "R@1,IoU=0.3": 0.0,
              "R@1,IoU=0.5": 0.0,
              "R@1,IoU=0.7": 0.0,
              "mIoU": 0.0,
              "count": 14,
              "R@5,mIoU": 13.5119,
              "R@5,IoU=0.3": 28.5714,
              "R@5,IoU=0.5": 0.0,
              "R@5,IoU=0.7": 0.0
            }
          }
        },
        {
          "slice": "long(20-60s)",
          "count": 3,
          "ratio": 0.00095,
          "models_percent": {
            "CPL": {
              "R@1,IoU=0.3": 33.3333,
              "R@1,IoU=0.5": 33.3333,
              "R@1,IoU=0.7": 0.0,
              "mIoU": 36.571,
              "count": 3,
              "R@5,mIoU": 74.1523,
              "R@5,IoU=0.3": 100.0,
              "R@5,IoU=0.5": 100.0,
              "R@5,IoU=0.7": 66.6667
            },
            "CPL_MoE": {
              "R@1,IoU=0.3": 100.0,
              "R@1,IoU=0.5": 33.3333,
              "R@1,IoU=0.7": 33.3333,
              "mIoU": 55.3074,
              "count": 3,
              "R@5,mIoU": 74.1765,
              "R@5,IoU=0.3": 100.0,
              "R@5,IoU=0.5": 100.0,
              "R@5,IoU=0.7": 100.0
            },
            "CPL_DMVS": {
              "R@1,IoU=0.3": 66.6667,
              "R@1,IoU=0.5": 0.0,
              "R@1,IoU=0.7": 0.0,
              "mIoU": 33.8794,
              "count": 3,
              "R@5,mIoU": 76.5706,
              "R@5,IoU=0.3": 100.0,
              "R@5,IoU=0.5": 100.0,
              "R@5,IoU=0.7": 100.0
            }
          }
        }
      ]
    },
    "starts_at_beginning": {
      "dimension": "starts_at_beginning",
      "num_slices": 2,
      "slices": [
        {
          "slice": "False",
          "count": 2201,
          "ratio": 0.69696,
          "models_percent": {
            "CPL": {
              "R@1,IoU=0.3": 66.3335,
              "R@1,IoU=0.5": 46.5243,
              "R@1,IoU=0.7": 19.6729,
              "mIoU": 42.296,
              "count": 2201,
              "R@5,mIoU": 66.5439,
              "R@5,IoU=0.3": 98.8642,
              "R@5,IoU=0.5": 85.0068,
              "R@5,IoU=0.7": 46.9332
            },
            "CPL_MoE": {
              "R@1,IoU=0.3": 66.8333,
              "R@1,IoU=0.5": 47.5239,
              "R@1,IoU=0.7": 18.2644,
              "mIoU": 42.3076,
              "count": 2201,
              "R@5,mIoU": 66.0131,
              "R@5,IoU=0.3": 98.8642,
              "R@5,IoU=0.5": 85.2794,
              "R@5,IoU=0.7": 45.343
            },
            "CPL_DMVS": {
              "R@1,IoU=0.3": 43.7528,
              "R@1,IoU=0.5": 27.5329,
              "R@1,IoU=0.7": 10.5407,
              "mIoU": 28.1945,
              "count": 2201,
              "R@5,mIoU": 62.9134,
              "R@5,IoU=0.3": 95.9564,
              "R@5,IoU=0.5": 77.0104,
              "R@5,IoU=0.7": 40.2999
            }
          }
        },
        {
          "slice": "True",
          "count": 957,
          "ratio": 0.30304,
          "models_percent": {
            "CPL": {
              "R@1,IoU=0.3": 65.4127,
              "R@1,IoU=0.5": 50.6792,
              "R@1,IoU=0.7": 29.8851,
              "mIoU": 45.2379,
              "count": 957,
              "R@5,mIoU": 66.8629,
              "R@5,IoU=0.3": 92.4765,
              "R@5,IoU=0.5": 77.534,
              "R@5,IoU=0.7": 56.0084
            },
            "CPL_MoE": {
              "R@1,IoU=0.3": 58.6207,
              "R@1,IoU=0.5": 43.1557,
              "R@1,IoU=0.7": 28.5266,
              "mIoU": 40.2103,
              "count": 957,
              "R@5,mIoU": 66.9159,
              "R@5,IoU=0.3": 94.0439,
              "R@5,IoU=0.5": 77.9519,
              "R@5,IoU=0.7": 55.5904
            },
            "CPL_DMVS": {
              "R@1,IoU=0.3": 24.0334,
              "R@1,IoU=0.5": 17.4504,
              "R@1,IoU=0.7": 8.8819,
              "mIoU": 17.1966,
              "count": 957,
              "R@5,mIoU": 55.7599,
              "R@5,IoU=0.3": 79.3103,
              "R@5,IoU=0.5": 63.4274,
              "R@5,IoU=0.7": 39.3939
            }
          }
        }
      ]
    },
    "ends_at_end": {
      "dimension": "ends_at_end",
      "num_slices": 2,
      "slices": [
        {
          "slice": "False",
          "count": 3055,
          "ratio": 0.967384,
          "models_percent": {
            "CPL": {
              "R@1,IoU=0.3": 66.6776,
              "R@1,IoU=0.5": 48.0524,
              "R@1,IoU=0.7": 22.6514,
              "mIoU": 43.4676,
              "count": 3055,
              "R@5,mIoU": 66.5244,
              "R@5,IoU=0.3": 97.0213,
              "R@5,IoU=0.5": 82.6187,
              "R@5,IoU=0.7": 49.1326
            },
            "CPL_MoE": {
              "R@1,IoU=0.3": 64.7791,
              "R@1,IoU=0.5": 46.4157,
              "R@1,IoU=0.7": 21.3421,
              "mIoU": 41.8442,
              "count": 3055,
              "R@5,mIoU": 66.1665,
              "R@5,IoU=0.3": 97.4468,
              "R@5,IoU=0.5": 82.8478,
              "R@5,IoU=0.7": 47.9869
            },
            "CPL_DMVS": {
              "R@1,IoU=0.3": 37.3813,
              "R@1,IoU=0.5": 23.928,
              "R@1,IoU=0.7": 9.5908,
              "mIoU": 24.5004,
              "count": 3055,
              "R@5,mIoU": 60.5195,
              "R@5,IoU=0.3": 90.8347,
              "R@5,IoU=0.5": 72.5041,
              "R@5,IoU=0.7": 39.3453
            }
          }
        },
        {
          "slice": "True",
          "count": 103,
          "ratio": 0.032616,
          "models_percent": {
            "CPL": {
              "R@1,IoU=0.3": 47.5728,
              "R@1,IoU=0.5": 39.8058,
              "R@1,IoU=0.7": 26.2136,
              "mIoU": 34.8802,
              "count": 103,
              "R@5,mIoU": 70.0884,
              "R@5,IoU=0.3": 94.1748,
              "R@5,IoU=0.5": 86.4078,
              "R@5,IoU=0.7": 66.0194
            },
            "CPL_MoE": {
              "R@1,IoU=0.3": 51.4563,
              "R@1,IoU=0.5": 39.8058,
              "R@1,IoU=0.7": 22.3301,
              "mIoU": 36.5646,
              "count": 103,
              "R@5,mIoU": 69.8523,
              "R@5,IoU=0.3": 96.1165,
              "R@5,IoU=0.5": 89.3204,
              "R@5,IoU=0.7": 62.1359
            },
            "CPL_DMVS": {
              "R@1,IoU=0.3": 49.5146,
              "R@1,IoU=0.5": 40.7767,
              "R@1,IoU=0.7": 23.301,
              "mIoU": 35.5779,
              "count": 103,
              "R@5,mIoU": 67.4495,
              "R@5,IoU=0.3": 93.2039,
              "R@5,IoU=0.5": 84.466,
              "R@5,IoU=0.7": 60.1942
            }
          }
        }
      ]
    },
    "query_density_bucket": {
      "dimension": "query_density_bucket",
      "num_slices": 4,
      "slices": [
        {
          "slice": "sparse(2-3)",
          "count": 1281,
          "ratio": 0.405636,
          "models_percent": {
            "CPL": {
              "R@1,IoU=0.3": 66.9009,
              "R@1,IoU=0.5": 48.3216,
              "R@1,IoU=0.7": 23.185,
              "mIoU": 43.8256,
              "count": 1281,
              "R@5,mIoU": 66.7867,
              "R@5,IoU=0.3": 96.7213,
              "R@5,IoU=0.5": 82.4356,
              "R@5,IoU=0.7": 50.2732
            },
            "CPL_MoE": {
              "R@1,IoU=0.3": 66.9789,
              "R@1,IoU=0.5": 48.79,
              "R@1,IoU=0.7": 22.0141,
              "mIoU": 43.2344,
              "count": 1281,
              "R@5,mIoU": 66.4054,
              "R@5,IoU=0.3": 97.58,
              "R@5,IoU=0.5": 82.982,
              "R@5,IoU=0.7": 49.4145
            },
            "CPL_DMVS": {
              "R@1,IoU=0.3": 39.032,
              "R@1,IoU=0.5": 25.2147,
              "R@1,IoU=0.7": 11.007,
              "mIoU": 25.5367,
              "count": 1281,
              "R@5,mIoU": 60.0478,
              "R@5,IoU=0.3": 90.242,
              "R@5,IoU=0.5": 71.0383,
              "R@5,IoU=0.7": 39.6565
            }
          }
        },
        {
          "slice": "medium(4-6)",
          "count": 1211,
          "ratio": 0.383471,
          "models_percent": {
            "CPL": {
              "R@1,IoU=0.3": 65.7308,
              "R@1,IoU=0.5": 46.986,
              "R@1,IoU=0.7": 22.4608,
              "mIoU": 42.8359,
              "count": 1211,
              "R@5,mIoU": 66.651,
              "R@5,IoU=0.3": 96.9447,
              "R@5,IoU=0.5": 82.5764,
              "R@5,IoU=0.7": 49.6284
            },
            "CPL_MoE": {
              "R@1,IoU=0.3": 63.4187,
              "R@1,IoU=0.5": 44.4261,
              "R@1,IoU=0.7": 20.8092,
              "mIoU": 41.1052,
              "count": 1211,
              "R@5,mIoU": 66.3987,
              "R@5,IoU=0.3": 97.1924,
              "R@5,IoU=0.5": 82.9067,
              "R@5,IoU=0.7": 47.6466
            },
            "CPL_DMVS": {
              "R@1,IoU=0.3": 37.2419,
              "R@1,IoU=0.5": 24.5252,
              "R@1,IoU=0.7": 9.0834,
              "mIoU": 24.4651,
              "count": 1211,
              "R@5,mIoU": 61.5441,
              "R@5,IoU=0.3": 91.4946,
              "R@5,IoU=0.5": 74.5665,
              "R@5,IoU=0.7": 40.9579
            }
          }
        },
        {
          "slice": "single_query",
          "count": 404,
          "ratio": 0.127929,
          "models_percent": {
            "CPL": {
              "R@1,IoU=0.3": 63.6139,
              "R@1,IoU=0.5": 47.5248,
              "R@1,IoU=0.7": 20.5446,
              "mIoU": 41.2513,
              "count": 404,
              "R@5,mIoU": 66.6898,
              "R@5,IoU=0.3": 98.2673,
              "R@5,IoU=0.5": 84.4059,
              "R@5,IoU=0.7": 48.7624
            },
            "CPL_MoE": {
              "R@1,IoU=0.3": 61.6337,
              "R@1,IoU=0.5": 45.0495,
              "R@1,IoU=0.7": 20.0495,
              "mIoU": 39.3865,
              "count": 404,
              "R@5,mIoU": 66.592,
              "R@5,IoU=0.3": 97.7723,
              "R@5,IoU=0.5": 84.901,
              "R@5,IoU=0.7": 50.495
            },
            "CPL_DMVS": {
              "R@1,IoU=0.3": 36.1386,
              "R@1,IoU=0.5": 24.0099,
              "R@1,IoU=0.7": 10.1485,
              "mIoU": 24.4515,
              "count": 404,
              "R@5,mIoU": 61.2218,
              "R@5,IoU=0.3": 91.5842,
              "R@5,IoU=0.5": 73.7624,
              "R@5,IoU=0.7": 40.8416
            }
          }
        },
        {
          "slice": "dense(7+)",
          "count": 262,
          "ratio": 0.082964,
          "models_percent": {
            "CPL": {
              "R@1,IoU=0.3": 67.1756,
              "R@1,IoU=0.5": 49.2366,
              "R@1,IoU=0.7": 25.5725,
              "mIoU": 44.6787,
              "count": 262,
              "R@5,mIoU": 65.8024,
              "R@5,IoU=0.3": 95.8015,
              "R@5,IoU=0.5": 82.4427,
              "R@5,IoU=0.7": 48.4733
            },
            "CPL_MoE": {
              "R@1,IoU=0.3": 59.9237,
              "R@1,IoU=0.5": 43.5115,
              "R@1,IoU=0.7": 22.9008,
              "mIoU": 40.1771,
              "count": 262,
              "R@5,mIoU": 64.7179,
              "R@5,IoU=0.3": 96.9466,
              "R@5,IoU=0.5": 81.2977,
              "R@5,IoU=0.7": 44.2748
            },
            "CPL_DMVS": {
              "R@1,IoU=0.3": 36.6412,
              "R@1,IoU=0.5": 21.374,
              "R@1,IoU=0.7": 9.542,
              "mIoU": 24.0277,
              "count": 262,
              "R@5,mIoU": 59.7318,
              "R@5,IoU=0.3": 90.458,
              "R@5,IoU=0.5": 72.9008,
              "R@5,IoU=0.7": 36.2595
            }
          }
        }
      ]
    },
    "has_overlapping_queries": {
      "dimension": "has_overlapping_queries",
      "num_slices": 2,
      "slices": [
        {
          "slice": "True",
          "count": 2505,
          "ratio": 0.793224,
          "models_percent": {
            "CPL": {
              "R@1,IoU=0.3": 67.2255,
              "R@1,IoU=0.5": 48.5429,
              "R@1,IoU=0.7": 23.4331,
              "mIoU": 43.9925,
              "count": 2505,
              "R@5,mIoU": 66.8704,
              "R@5,IoU=0.3": 96.8463,
              "R@5,IoU=0.5": 82.9142,
              "R@5,IoU=0.7": 50.3393
            },
            "CPL_MoE": {
              "R@1,IoU=0.3": 64.99,
              "R@1,IoU=0.5": 46.8663,
              "R@1,IoU=0.7": 21.8762,
              "mIoU": 42.1823,
              "count": 2505,
              "R@5,mIoU": 66.6462,
              "R@5,IoU=0.3": 97.6048,
              "R@5,IoU=0.5": 83.5529,
              "R@5,IoU=0.7": 49.1417
            },
            "CPL_DMVS": {
              "R@1,IoU=0.3": 37.8044,
              "R@1,IoU=0.5": 24.6707,
              "R@1,IoU=0.7": 9.8204,
              "mIoU": 24.8452,
              "count": 2505,
              "R@5,mIoU": 60.6972,
              "R@5,IoU=0.3": 90.7385,
              "R@5,IoU=0.5": 72.6946,
              "R@5,IoU=0.7": 39.9202
            }
          }
        },
        {
          "slice": "False",
          "count": 653,
          "ratio": 0.206776,
          "models_percent": {
            "CPL": {
              "R@1,IoU=0.3": 61.562,
              "R@1,IoU=0.5": 44.8698,
              "R@1,IoU=0.7": 20.2144,
              "mIoU": 40.0997,
              "count": 653,
              "R@5,mIoU": 65.759,
              "R@5,IoU=0.3": 97.2435,
              "R@5,IoU=0.5": 82.0827,
              "R@5,IoU=0.7": 47.1669
            },
            "CPL_MoE": {
              "R@1,IoU=0.3": 61.8683,
              "R@1,IoU=0.5": 43.6447,
              "R@1,IoU=0.7": 19.4487,
              "mIoU": 39.7146,
              "count": 653,
              "R@5,mIoU": 64.9076,
              "R@5,IoU=0.3": 96.6309,
              "R@5,IoU=0.5": 81.1639,
              "R@5,IoU=0.7": 45.7887
            },
            "CPL_DMVS": {
              "R@1,IoU=0.3": 37.6723,
              "R@1,IoU=0.5": 23.7366,
              "R@1,IoU=0.7": 10.8729,
              "mIoU": 24.9253,
              "count": 653,
              "R@5,mIoU": 60.931,
              "R@5,IoU=0.3": 91.5773,
              "R@5,IoU=0.5": 73.66,
              "R@5,IoU=0.7": 40.4288
            }
          }
        }
      ]
    }
  },
  "divergences": [
    {
      "dimension": "gt_position_bucket",
      "slice": "beginning",
      "count": 1595,
      "metric": "R@1,IoU=0.5",
      "max_diff": 0.3467084639498432,
      "best_model": "CPL",
      "worst_model": "CPL_DMVS",
      "model_values": {
        "CPL": 0.5109717868338558,
        "CPL_MoE": 0.4269592476489028,
        "CPL_DMVS": 0.16426332288401255
      }
    },
    {
      "dimension": "starts_at_beginning",
      "slice": "True",
      "count": 957,
      "metric": "R@1,IoU=0.5",
      "max_diff": 0.3322884012539185,
      "best_model": "CPL",
      "worst_model": "CPL_DMVS",
      "model_values": {
        "CPL": 0.5067920585161965,
        "CPL_MoE": 0.4315569487983281,
        "CPL_DMVS": 0.17450365726227796
      }
    },
    {
      "dimension": "action_category",
      "slice": "interaction,movement",
      "count": 63,
      "metric": "R@1,IoU=0.5",
      "max_diff": 0.3174603174603175,
      "best_model": "CPL_MoE",
      "worst_model": "CPL_DMVS",
      "model_values": {
        "CPL": 0.5873015873015873,
        "CPL_MoE": 0.6190476190476191,
        "CPL_DMVS": 0.30158730158730157
      }
    },
    {
      "dimension": "gt_length_bucket",
      "slice": "medium(8-20s)",
      "count": 1182,
      "metric": "R@1,IoU=0.5",
      "max_diff": 0.29780033840947545,
      "best_model": "CPL",
      "worst_model": "CPL_DMVS",
      "model_values": {
        "CPL": 0.6015228426395939,
        "CPL_MoE": 0.5685279187817259,
        "CPL_DMVS": 0.30372250423011843
      }
    },
    {
      "dimension": "action_category",
      "slice": "state_change",
      "count": 807,
      "metric": "R@1,IoU=0.5",
      "max_diff": 0.2800495662949195,
      "best_model": "CPL",
      "worst_model": "CPL_DMVS",
      "model_values": {
        "CPL": 0.4721189591078067,
        "CPL_MoE": 0.46964064436183395,
        "CPL_DMVS": 0.19206939281288724
      }
    },
    {
      "dimension": "gt_coverage_bucket",
      "slice": "medium(30-50%)",
      "count": 1068,
      "metric": "R@1,IoU=0.5",
      "max_diff": 0.2790262172284644,
      "best_model": "CPL",
      "worst_model": "CPL_DMVS",
      "model_values": {
        "CPL": 0.6217228464419475,
        "CPL_MoE": 0.5795880149812734,
        "CPL_DMVS": 0.34269662921348315
      }
    },
    {
      "dimension": "query_density_bucket",
      "slice": "dense(7+)",
      "count": 262,
      "metric": "R@1,IoU=0.5",
      "max_diff": 0.27862595419847325,
      "best_model": "CPL",
      "worst_model": "CPL_DMVS",
      "model_values": {
        "CPL": 0.49236641221374045,
        "CPL_MoE": 0.4351145038167939,
        "CPL_DMVS": 0.21374045801526717
      }
    },
    {
      "dimension": "action_category",
      "slice": "movement,state_change",
      "count": 33,
      "metric": "R@1,IoU=0.5",
      "max_diff": 0.2727272727272727,
      "best_model": "CPL_MoE",
      "worst_model": "CPL_DMVS",
      "model_values": {
        "CPL": 0.45454545454545453,
        "CPL_MoE": 0.48484848484848486,
        "CPL_DMVS": 0.21212121212121213
      }
    },
    {
      "dimension": "action_category",
      "slice": "perception",
      "count": 496,
      "metric": "R@1,IoU=0.5",
      "max_diff": 0.2620967741935484,
      "best_model": "CPL",
      "worst_model": "CPL_DMVS",
      "model_values": {
        "CPL": 0.5161290322580645,
        "CPL_MoE": 0.46774193548387094,
        "CPL_DMVS": 0.2540322580645161
      }
    },
    {
      "dimension": "video_length_bucket",
      "slice": "very_short(<=20s)",
      "count": 351,
      "metric": "R@1,IoU=0.5",
      "max_diff": 0.2592592592592593,
      "best_model": "CPL",
      "worst_model": "CPL_DMVS",
      "model_values": {
        "CPL": 0.6096866096866097,
        "CPL_MoE": 0.4985754985754986,
        "CPL_DMVS": 0.3504273504273504
      }
    },
    {
      "dimension": "action_category",
      "slice": "interaction,perception",
      "count": 56,
      "metric": "R@1,IoU=0.5",
      "max_diff": 0.25,
      "best_model": "CPL_MoE",
      "worst_model": "CPL_DMVS",
      "model_values": {
        "CPL": 0.42857142857142855,
        "CPL_MoE": 0.4642857142857143,
        "CPL_DMVS": 0.21428571428571427
      }
    },
    {
      "dimension": "action_complexity",
      "slice": "single_action",
      "count": 2381,
      "metric": "R@1,IoU=0.5",
      "max_diff": 0.24275514489710204,
      "best_model": "CPL",
      "worst_model": "CPL_DMVS",
      "model_values": {
        "CPL": 0.48089038219235614,
        "CPL_MoE": 0.46745065098698024,
        "CPL_DMVS": 0.2381352372952541
      }
    },
    {
      "dimension": "ends_at_end",
      "slice": "False",
      "count": 3055,
      "metric": "R@1,IoU=0.5",
      "max_diff": 0.2412438625204583,
      "best_model": "CPL",
      "worst_model": "CPL_DMVS",
      "model_values": {
        "CPL": 0.4805237315875614,
        "CPL_MoE": 0.4641571194762684,
        "CPL_DMVS": 0.2392798690671031
      }
    },
    {
      "dimension": "has_overlapping_queries",
      "slice": "True",
      "count": 2505,
      "metric": "R@1,IoU=0.5",
      "max_diff": 0.23872255489021957,
      "best_model": "CPL",
      "worst_model": "CPL_DMVS",
      "model_values": {
        "CPL": 0.48542914171656687,
        "CPL_MoE": 0.4686626746506986,
        "CPL_DMVS": 0.2467065868263473
      }
    },
    {
      "dimension": "has_temporal_cue",
      "slice": "False",
      "count": 3051,
      "metric": "R@1,IoU=0.5",
      "max_diff": 0.23795476892822026,
      "best_model": "CPL",
      "worst_model": "CPL_DMVS",
      "model_values": {
        "CPL": 0.47885939036381514,
        "CPL_MoE": 0.46214355948869223,
        "CPL_DMVS": 0.24090462143559488
      }
    },
    {
      "dimension": "query_density_bucket",
      "slice": "sparse(2-3)",
      "count": 1281,
      "metric": "R@1,IoU=0.5",
      "max_diff": 0.23575331772053082,
      "best_model": "CPL_MoE",
      "worst_model": "CPL_DMVS",
      "model_values": {
        "CPL": 0.48321623731459795,
        "CPL_MoE": 0.4879000780640125,
        "CPL_DMVS": 0.25214676034348166
      }
    },
    {
      "dimension": "query_density_bucket",
      "slice": "single_query",
      "count": 404,
      "metric": "R@1,IoU=0.5",
      "max_diff": 0.23514851485148514,
      "best_model": "CPL",
      "worst_model": "CPL_DMVS",
      "model_values": {
        "CPL": 0.4752475247524752,
        "CPL_MoE": 0.4504950495049505,
        "CPL_DMVS": 0.2400990099009901
      }
    },
    {
      "dimension": "query_length_bucket",
      "slice": "medium(6-10)",
      "count": 1914,
      "metric": "R@1,IoU=0.5",
      "max_diff": 0.23510971786833854,
      "best_model": "CPL",
      "worst_model": "CPL_DMVS",
      "model_values": {
        "CPL": 0.47492163009404387,
        "CPL_MoE": 0.455067920585162,
        "CPL_DMVS": 0.23981191222570533
      }
    },
    {
      "dimension": "has_person_subject",
      "slice": "True",
      "count": 3155,
      "metric": "R@1,IoU=0.5",
      "max_diff": 0.2329635499207607,
      "best_model": "CPL",
      "worst_model": "CPL_DMVS",
      "model_values": {
        "CPL": 0.4779714738510301,
        "CPL_MoE": 0.46212361331220286,
        "CPL_DMVS": 0.2450079239302694
      }
    },
    {
      "dimension": "video_length_bucket",
      "slice": "short(20-40s)",
      "count": 2608,
      "metric": "R@1,IoU=0.5",
      "max_diff": 0.23274539877300612,
      "best_model": "CPL",
      "worst_model": "CPL_DMVS",
      "model_values": {
        "CPL": 0.46894171779141103,
        "CPL_MoE": 0.4647239263803681,
        "CPL_DMVS": 0.2361963190184049
      }
    },
    {
      "dimension": "action_complexity",
      "slice": "no_verb",
      "count": 234,
      "metric": "R@1,IoU=0.5",
      "max_diff": 0.23076923076923073,
      "best_model": "CPL",
      "worst_model": "CPL_DMVS",
      "model_values": {
        "CPL": 0.49145299145299143,
        "CPL_MoE": 0.4700854700854701,
        "CPL_DMVS": 0.2606837606837607
      }
    },
    {
      "dimension": "action_category",
      "slice": "unknown",
      "count": 234,
      "metric": "R@1,IoU=0.5",
      "max_diff": 0.23076923076923073,
      "best_model": "CPL",
      "worst_model": "CPL_DMVS",
      "model_values": {
        "CPL": 0.49145299145299143,
        "CPL_MoE": 0.4700854700854701,
        "CPL_DMVS": 0.2606837606837607
      }
    },
    {
      "dimension": "query_length_bucket",
      "slice": "short(<=5)",
      "count": 1243,
      "metric": "R@1,IoU=0.5",
      "max_diff": 0.22928399034593727,
      "best_model": "CPL",
      "worst_model": "CPL_DMVS",
      "model_values": {
        "CPL": 0.48189863234111024,
        "CPL_MoE": 0.47224456958970235,
        "CPL_DMVS": 0.252614641995173
      }
    },
    {
      "dimension": "query_density_bucket",
      "slice": "medium(4-6)",
      "count": 1211,
      "metric": "R@1,IoU=0.5",
      "max_diff": 0.2246077621800165,
      "best_model": "CPL",
      "worst_model": "CPL_DMVS",
      "model_values": {
        "CPL": 0.46985962014863747,
        "CPL_MoE": 0.44426094137076794,
        "CPL_DMVS": 0.24525185796862098
      }
    },
    {
      "dimension": "action_category",
      "slice": "interaction",
      "count": 945,
      "metric": "R@1,IoU=0.5",
      "max_diff": 0.22116402116402117,
      "best_model": "CPL",
      "worst_model": "CPL_DMVS",
      "model_values": {
        "CPL": 0.4486772486772487,
        "CPL_MoE": 0.4402116402116402,
        "CPL_DMVS": 0.2275132275132275
      }
    },
    {
      "dimension": "gt_coverage_bucket",
      "slice": "small(10-30%)",
      "count": 2052,
      "metric": "R@1,IoU=0.5",
      "max_diff": 0.21345029239766083,
      "best_model": "CPL",
      "worst_model": "CPL_DMVS",
      "model_values": {
        "CPL": 0.4083820662768031,
        "CPL_MoE": 0.4064327485380117,
        "CPL_DMVS": 0.1949317738791423
      }
    },
    {
      "dimension": "has_overlapping_queries",
      "slice": "False",
      "count": 653,
      "metric": "R@1,IoU=0.5",
      "max_diff": 0.21133231240428793,
      "best_model": "CPL",
      "worst_model": "CPL_DMVS",
      "model_values": {
        "CPL": 0.44869831546707506,
        "CPL_MoE": 0.43644716692189894,
        "CPL_DMVS": 0.23736600306278713
      }
    },
    {
      "dimension": "starts_at_beginning",
      "slice": "False",
      "count": 2201,
      "metric": "R@1,IoU=0.5",
      "max_diff": 0.19990913221263062,
      "best_model": "CPL_MoE",
      "worst_model": "CPL_DMVS",
      "model_values": {
        "CPL": 0.46524307133121307,
        "CPL_MoE": 0.4752385279418446,
        "CPL_DMVS": 0.275329395729214
      }
    },
    {
      "dimension": "action_complexity",
      "slice": "dual_action",
      "count": 517,
      "metric": "R@1,IoU=0.5",
      "max_diff": 0.19729206963249518,
      "best_model": "CPL",
      "worst_model": "CPL_DMVS",
      "model_values": {
        "CPL": 0.4584139264990329,
        "CPL_MoE": 0.43133462282398455,
        "CPL_DMVS": 0.2611218568665377
      }
    },
    {
      "dimension": "gt_length_bucket",
      "slice": "short(3-8s)",
      "count": 1959,
      "metric": "R@1,IoU=0.5",
      "max_diff": 0.19499744767738642,
      "best_model": "CPL",
      "worst_model": "CPL_DMVS",
      "model_values": {
        "CPL": 0.4063297600816743,
        "CPL_MoE": 0.4012251148545176,
        "CPL_DMVS": 0.2113323124042879
      }
    },
    {
      "dimension": "video_length_bucket",
      "slice": "medium(40-80s)",
      "count": 199,
      "metric": "R@1,IoU=0.5",
      "max_diff": 0.19095477386934676,
      "best_model": "CPL",
      "worst_model": "CPL_DMVS",
      "model_values": {
        "CPL": 0.36180904522613067,
        "CPL_MoE": 0.36180904522613067,
        "CPL_DMVS": 0.1708542713567839
      }
    },
    {
      "dimension": "gt_position_bucket",
      "slice": "end",
      "count": 565,
      "metric": "R@1,IoU=0.5",
      "max_diff": 0.17345132743362834,
      "best_model": "CPL_MoE",
      "worst_model": "CPL_DMVS",
      "model_values": {
        "CPL": 0.48849557522123893,
        "CPL_MoE": 0.5415929203539823,
        "CPL_DMVS": 0.368141592920354
      }
    },
    {
      "dimension": "gt_position_bucket",
      "slice": "middle",
      "count": 998,
      "metric": "R@1,IoU=0.5",
      "max_diff": 0.16933867735470937,
      "best_model": "CPL_MoE",
      "worst_model": "CPL_DMVS",
      "model_values": {
        "CPL": 0.4188376753507014,
        "CPL_MoE": 0.4729458917835671,
        "CPL_DMVS": 0.30360721442885774
      }
    },
    {
      "dimension": "action_category",
      "slice": "movement",
      "count": 325,
      "metric": "R@1,IoU=0.5",
      "max_diff": 0.16307692307692306,
      "best_model": "CPL",
      "worst_model": "CPL_DMVS",
      "model_values": {
        "CPL": 0.5446153846153846,
        "CPL_MoE": 0.5046153846153846,
        "CPL_DMVS": 0.38153846153846155
      }
    },
    {
      "dimension": "action_category",
      "slice": "perception,state_change",
      "count": 68,
      "metric": "R@1,IoU=0.5",
      "max_diff": 0.16176470588235298,
      "best_model": "CPL",
      "worst_model": "CPL_DMVS",
      "model_values": {
        "CPL": 0.36764705882352944,
        "CPL_MoE": 0.3382352941176471,
        "CPL_DMVS": 0.20588235294117646
      }
    },
    {
      "dimension": "action_category",
      "slice": "movement,perception",
      "count": 76,
      "metric": "R@1,IoU=0.5",
      "max_diff": 0.15789473684210525,
      "best_model": "CPL",
      "worst_model": "CPL_DMVS",
      "model_values": {
        "CPL": 0.47368421052631576,
        "CPL_MoE": 0.39473684210526316,
        "CPL_DMVS": 0.3157894736842105
      }
    },
    {
      "dimension": "action_category",
      "slice": "interaction,state_change",
      "count": 49,
      "metric": "R@1,IoU=0.5",
      "max_diff": 0.1224489795918367,
      "best_model": "CPL_MoE",
      "worst_model": "CPL_DMVS",
      "model_values": {
        "CPL": 0.32653061224489793,
        "CPL_MoE": 0.42857142857142855,
        "CPL_DMVS": 0.30612244897959184
      }
    },
    {
      "dimension": "has_temporal_cue",
      "slice": "True",
      "count": 107,
      "metric": "R@1,IoU=0.5",
      "max_diff": 0.10280373831775702,
      "best_model": "CPL_MoE",
      "worst_model": "CPL_DMVS",
      "model_values": {
        "CPL": 0.4485981308411215,
        "CPL_MoE": 0.45794392523364486,
        "CPL_DMVS": 0.35514018691588783
      }
    },
    {
      "dimension": "ends_at_end",
      "slice": "True",
      "count": 103,
      "metric": "R@1,IoU=0.5",
      "max_diff": 0.009708737864077666,
      "best_model": "CPL_DMVS",
      "worst_model": "CPL",
      "model_values": {
        "CPL": 0.39805825242718446,
        "CPL_MoE": 0.39805825242718446,
        "CPL_DMVS": 0.4077669902912621
      }
    }
  ],
  "strengths": {
    "CPL": {
      "best_slices": [
        {
          "dimension": "gt_coverage_bucket",
          "slice": "medium(30-50%)",
          "count": 1068,
          "R@1,IoU=0.5": 0.6217228464419475
        },
        {
          "dimension": "video_length_bucket",
          "slice": "very_short(<=20s)",
          "count": 351,
          "R@1,IoU=0.5": 0.6096866096866097
        },
        {
          "dimension": "gt_length_bucket",
          "slice": "medium(8-20s)",
          "count": 1182,
          "R@1,IoU=0.5": 0.6015228426395939
        },
        {
          "dimension": "action_category",
          "slice": "interaction,movement",
          "count": 63,
          "R@1,IoU=0.5": 0.5873015873015873
        },
        {
          "dimension": "action_category",
          "slice": "movement",
          "count": 325,
          "R@1,IoU=0.5": 0.5446153846153846
        },
        {
          "dimension": "action_category",
          "slice": "perception",
          "count": 496,
          "R@1,IoU=0.5": 0.5161290322580645
        },
        {
          "dimension": "gt_position_bucket",
          "slice": "beginning",
          "count": 1595,
          "R@1,IoU=0.5": 0.5109717868338558
        },
        {
          "dimension": "starts_at_beginning",
          "slice": "True",
          "count": 957,
          "R@1,IoU=0.5": 0.5067920585161965
        },
        {
          "dimension": "query_density_bucket",
          "slice": "dense(7+)",
          "count": 262,
          "R@1,IoU=0.5": 0.49236641221374045
        },
        {
          "dimension": "action_complexity",
          "slice": "no_verb",
          "count": 234,
          "R@1,IoU=0.5": 0.49145299145299143
        }
      ],
      "worst_slices": [
        {
          "dimension": "action_category",
          "slice": "interaction,state_change",
          "count": 49,
          "R@1,IoU=0.5": 0.32653061224489793
        },
        {
          "dimension": "video_length_bucket",
          "slice": "medium(40-80s)",
          "count": 199,
          "R@1,IoU=0.5": 0.36180904522613067
        },
        {
          "dimension": "action_category",
          "slice": "perception,state_change",
          "count": 68,
          "R@1,IoU=0.5": 0.36764705882352944
        },
        {
          "dimension": "ends_at_end",
          "slice": "True",
          "count": 103,
          "R@1,IoU=0.5": 0.39805825242718446
        },
        {
          "dimension": "gt_length_bucket",
          "slice": "short(3-8s)",
          "count": 1959,
          "R@1,IoU=0.5": 0.4063297600816743
        },
        {
          "dimension": "gt_coverage_bucket",
          "slice": "small(10-30%)",
          "count": 2052,
          "R@1,IoU=0.5": 0.4083820662768031
        },
        {
          "dimension": "gt_position_bucket",
          "slice": "middle",
          "count": 998,
          "R@1,IoU=0.5": 0.4188376753507014
        },
        {
          "dimension": "action_category",
          "slice": "interaction,perception",
          "count": 56,
          "R@1,IoU=0.5": 0.42857142857142855
        },
        {
          "dimension": "has_temporal_cue",
          "slice": "True",
          "count": 107,
          "R@1,IoU=0.5": 0.4485981308411215
        },
        {
          "dimension": "action_category",
          "slice": "interaction",
          "count": 945,
          "R@1,IoU=0.5": 0.4486772486772487
        }
      ]
    },
    "CPL_MoE": {
      "best_slices": [
        {
          "dimension": "action_category",
          "slice": "interaction,movement",
          "count": 63,
          "R@1,IoU=0.5": 0.6190476190476191
        },
        {
          "dimension": "gt_coverage_bucket",
          "slice": "medium(30-50%)",
          "count": 1068,
          "R@1,IoU=0.5": 0.5795880149812734
        },
        {
          "dimension": "gt_length_bucket",
          "slice": "medium(8-20s)",
          "count": 1182,
          "R@1,IoU=0.5": 0.5685279187817259
        },
        {
          "dimension": "gt_position_bucket",
          "slice": "end",
          "count": 565,
          "R@1,IoU=0.5": 0.5415929203539823
        },
        {
          "dimension": "action_category",
          "slice": "movement",
          "count": 325,
          "R@1,IoU=0.5": 0.5046153846153846
        },
        {
          "dimension": "video_length_bucket",
          "slice": "very_short(<=20s)",
          "count": 351,
          "R@1,IoU=0.5": 0.4985754985754986
        },
        {
          "dimension": "query_density_bucket",
          "slice": "sparse(2-3)",
          "count": 1281,
          "R@1,IoU=0.5": 0.4879000780640125
        },
        {
          "dimension": "action_category",
          "slice": "movement,state_change",
          "count": 33,
          "R@1,IoU=0.5": 0.48484848484848486
        },
        {
          "dimension": "starts_at_beginning",
          "slice": "False",
          "count": 2201,
          "R@1,IoU=0.5": 0.4752385279418446
        },
        {
          "dimension": "gt_position_bucket",
          "slice": "middle",
          "count": 998,
          "R@1,IoU=0.5": 0.4729458917835671
        }
      ],
      "worst_slices": [
        {
          "dimension": "action_category",
          "slice": "perception,state_change",
          "count": 68,
          "R@1,IoU=0.5": 0.3382352941176471
        },
        {
          "dimension": "video_length_bucket",
          "slice": "medium(40-80s)",
          "count": 199,
          "R@1,IoU=0.5": 0.36180904522613067
        },
        {
          "dimension": "action_category",
          "slice": "movement,perception",
          "count": 76,
          "R@1,IoU=0.5": 0.39473684210526316
        },
        {
          "dimension": "ends_at_end",
          "slice": "True",
          "count": 103,
          "R@1,IoU=0.5": 0.39805825242718446
        },
        {
          "dimension": "gt_length_bucket",
          "slice": "short(3-8s)",
          "count": 1959,
          "R@1,IoU=0.5": 0.4012251148545176
        },
        {
          "dimension": "gt_coverage_bucket",
          "slice": "small(10-30%)",
          "count": 2052,
          "R@1,IoU=0.5": 0.4064327485380117
        },
        {
          "dimension": "gt_position_bucket",
          "slice": "beginning",
          "count": 1595,
          "R@1,IoU=0.5": 0.4269592476489028
        },
        {
          "dimension": "action_category",
          "slice": "interaction,state_change",
          "count": 49,
          "R@1,IoU=0.5": 0.42857142857142855
        },
        {
          "dimension": "action_complexity",
          "slice": "dual_action",
          "count": 517,
          "R@1,IoU=0.5": 0.43133462282398455
        },
        {
          "dimension": "starts_at_beginning",
          "slice": "True",
          "count": 957,
          "R@1,IoU=0.5": 0.4315569487983281
        }
      ]
    },
    "CPL_DMVS": {
      "best_slices": [
        {
          "dimension": "ends_at_end",
          "slice": "True",
          "count": 103,
          "R@1,IoU=0.5": 0.4077669902912621
        },
        {
          "dimension": "action_category",
          "slice": "movement",
          "count": 325,
          "R@1,IoU=0.5": 0.38153846153846155
        },
        {
          "dimension": "gt_position_bucket",
          "slice": "end",
          "count": 565,
          "R@1,IoU=0.5": 0.368141592920354
        },
        {
          "dimension": "has_temporal_cue",
          "slice": "True",
          "count": 107,
          "R@1,IoU=0.5": 0.35514018691588783
        },
        {
          "dimension": "video_length_bucket",
          "slice": "very_short(<=20s)",
          "count": 351,
          "R@1,IoU=0.5": 0.3504273504273504
        },
        {
          "dimension": "gt_coverage_bucket",
          "slice": "medium(30-50%)",
          "count": 1068,
          "R@1,IoU=0.5": 0.34269662921348315
        },
        {
          "dimension": "action_category",
          "slice": "movement,perception",
          "count": 76,
          "R@1,IoU=0.5": 0.3157894736842105
        },
        {
          "dimension": "action_category",
          "slice": "interaction,state_change",
          "count": 49,
          "R@1,IoU=0.5": 0.30612244897959184
        },
        {
          "dimension": "gt_length_bucket",
          "slice": "medium(8-20s)",
          "count": 1182,
          "R@1,IoU=0.5": 0.30372250423011843
        },
        {
          "dimension": "gt_position_bucket",
          "slice": "middle",
          "count": 998,
          "R@1,IoU=0.5": 0.30360721442885774
        }
      ],
      "worst_slices": [
        {
          "dimension": "gt_position_bucket",
          "slice": "beginning",
          "count": 1595,
          "R@1,IoU=0.5": 0.16426332288401255
        },
        {
          "dimension": "video_length_bucket",
          "slice": "medium(40-80s)",
          "count": 199,
          "R@1,IoU=0.5": 0.1708542713567839
        },
        {
          "dimension": "starts_at_beginning",
          "slice": "True",
          "count": 957,
          "R@1,IoU=0.5": 0.17450365726227796
        },
        {
          "dimension": "action_category",
          "slice": "state_change",
          "count": 807,
          "R@1,IoU=0.5": 0.19206939281288724
        },
        {
          "dimension": "gt_coverage_bucket",
          "slice": "small(10-30%)",
          "count": 2052,
          "R@1,IoU=0.5": 0.1949317738791423
        },
        {
          "dimension": "action_category",
          "slice": "perception,state_change",
          "count": 68,
          "R@1,IoU=0.5": 0.20588235294117646
        },
        {
          "dimension": "gt_length_bucket",
          "slice": "short(3-8s)",
          "count": 1959,
          "R@1,IoU=0.5": 0.2113323124042879
        },
        {
          "dimension": "action_category",
          "slice": "movement,state_change",
          "count": 33,
          "R@1,IoU=0.5": 0.21212121212121213
        },
        {
          "dimension": "query_density_bucket",
          "slice": "dense(7+)",
          "count": 262,
          "R@1,IoU=0.5": 0.21374045801526717
        },
        {
          "dimension": "action_category",
          "slice": "interaction,perception",
          "count": 56,
          "R@1,IoU=0.5": 0.21428571428571427
        }
      ]
    }
  }
}